Workbook

Sheet CARTERA
A1: Columna2 | B1: Columna1

Sheet Pedidos
A1: Esatdo Cartera | B1: ESTADO | C1: ID | D1: id_dropi | E1: fecha | F1: cliente | G1: transportadora | H1: estado_actualizado desde_app | I1: Estado de guia app (TEMP) | J1: estado_operativo | K1: guia | L1: despartamento | M1: ciudad | N1: direccion | O1: telefono | P1: Notas Manuales | Q1: notas | R1: Producto | S1: ganancia_calc | T1: costo_devolucion_estimado | U1: cartera | V1: cartera_aplicada | W1: venta | X1: flete | Y1: costo_proveedor | Z1: fecha_ult_mov | AA1: dias_desde_ult_mov | AB1: hora_ult_mov | AC1: ultimo_mov | AD1: estatus_original | AE1: estado_unificado
C2: 1062 | D2: 63461707 | E2: 46044 | F2: Gloria Del valle | G2: ENVIA | J2: PENDIENTE | L2: BOLIVAR | M2: CARTAGENA | N2: calle 5 #80e-45, barrio San Fernando | O2: 3243934970 | P2: {=IFERROR(_xlfn.XLOOKUP(tblPedidos[[#This Row],[id_dropi]],tblNotas[[#This Row],[id__dropi]],tblNotas[[#This Row],[Notas Manuales]], “”, 0),"")} | R2: Cepillo Plancha Secador 2 en 1 Alisador x1 | S2: 25511.5 | T2: -11990.8 | U2: {=IFERROR(_xlfn.IFS(tblPedidos[[#This Row],[estado_operativo]]="ENTREGADO",tblPedidos[[#This Row],[ganancia_calc]],tblPedidos[[#This Row],[estado_operativo]]="DEVOLUCION",tblPedidos[[#This Row],[costo_devolucion_estimado]]),0)} -> 0 | V2: 0 | W2: 54900 | X2: 14988.5 | Y2: 14400 | Z2: 46044 | AA2: 0 | AB2: 0.0020833333 | AC2: PENDIENTE | AD2: PENDIENTE | AE2: PENDIENTE
C3: 1061 | D3: 63461674 | E3: 46044 | F3: Nataly Montero Vquero | G3: INTERRAPIDISIMO | J3: PENDIENTE | L3: CUNDINAMARCA | M3: GUADUAS | N3: Cliente recoge pedido en oficina de Interrapidisimo en Guaduas cliente recoge en esa oficina | O3: 3142074177 | P3: {=IFERROR(_xlfn.XLOOKUP(tblPedidos[[#This Row],[id_dropi]],tblNotas[[#This Row],[id__dropi]],tblNotas[[#This Row],[Notas Manuales]], “”, 0),"")} | Q3: PEDIDO PARA RECOGER EN OFICINA DE INTERRAPIDISIMO | R3: Cepillo Plancha Secador 2 en 1 Alisador x2 | S3: 32079.5 | T3: -14020.5 | U3: {=IFERROR(_xlfn.IFS(tblPedidos[[#This Row],[estado_operativo]]="ENTREGADO",tblPedidos[[#This Row],[ganancia_calc]],tblPedidos[[#This Row],[estado_operativo]]="DEVOLUCION",tblPedidos[[#This Row],[costo_devolucion_estimado]]),0)} -> 0 | V3: 0 | W3: 74900 | X3: 14020.5 | Y3: 28800 | Z3: 46044 | AA3: 0 | AB3: 0.0020833333 | AC3: PENDIENTE | AD3: PENDIENTE | AE3: PENDIENTE
C4: 1064 | D4: 63461638 | E4: 46044 | F4: OrdaliZ Guzmán | G4: INTERRAPIDISIMO | J4: PENDIENTE | L4: ANTIOQUIA | M4: APARTADO | N4: Cliente recoge pedido en oficina de Interrapidisimo en Apartado cliente recoge en esa oficina | O4: 3108451453 | P4: {=IFERROR(_xlfn.XLOOKUP(tblPedidos[[#This Row],[id_dropi]],tblNotas[[#This Row],[id__dropi]],tblNotas[[#This Row],[Notas Manuales]], “”, 0),"")} | Q4: PEDIDO PARA RECOGER EN OFICINA DE INTERRAPIDISIMO | R4: Quemador de grasa Lemme Burn 60 cáps x2 | S4: 20654.5 | T4: -19245.5 | U4: {=IFERROR(_xlfn.IFS(tblPedidos[[#This Row],[estado_operativo]]="ENTREGADO",tblPedidos[[#This Row],[ganancia_calc]],tblPedidos[[#This Row],[estado_operativo]]="DEVOLUCION",tblPedidos[[#This Row],[costo_devolucion_estimado]]),0)} -> 0 | V4: 0 | W4: 89900 | X4: 19245.5 | Y4: 50000 | Z4: 46044 | AA4: 0 | AB4: 0.0013888889 | AC4: PENDIENTE | AD4: PENDIENTE | AE4: PENDIENTE
C5: 1063 | D5: 63461582 | E5: 46044 | F5: Rosalbina perdomo | G5: INTERRAPIDISIMO | J5: PENDIENTE | L5: CAQUETA | M5: FLORENCIA | N5: Calle 14 # 15 -68 barrio centro | O5: 3235021099 | P5: {=IFERROR(_xlfn.XLOOKUP(tblPedidos[[#This Row],[id_dropi]],tblNotas[[#This Row],[id__dropi]],tblNotas[[#This Row],[Notas Manuales]], “”, 0),"")} | R5: Bee Venom BSWELL x1 + Beevana crema +Varicose veins x1 | S5: 17004.5 | T5: -17895.5 | U5: {=IFERROR(_xlfn.IFS(tblPedidos[[#This Row],[estado_operativo]]="ENTREGADO",tblPedidos[[#This Row],[ganancia_calc]],tblPedidos[[#This Row],[estado_operativo]]="DEVOLUCION",tblPedidos[[#This Row],[costo_devolucion_estimado]]),0)} -> 0 | V5: 0 | W5: 59900 | X5: 17895.5 | Y5: 25000 | Z5: 46044 | AA5: 0 | AB5: 0 | AC5: PENDIENTE | AD5: PENDIENTE | AE5: PENDIENTE
C6: 1022 | D6: 63461491 | E6: 46043 | F6: Gloria Janeth Vanegas Mendoza | G6: INTERRAPIDISIMO | J6: PENDIENTE | L6: QUINDIO | M6: ARMENIA (Q) | N6: Barrio los arcades manzana K número 20 | O6: 3133277752 | P6: {=IFERROR(_xlfn.XLOOKUP(tblPedidos[[#This Row],[id_dropi]],tblNotas[[#This Row],[id__dropi]],tblNotas[[#This Row],[Notas Manuales]], “”, 0),"")} | R6: Bee Venom BSWELL x1 + Beevana crema +Varicose veins x1 | S6: 17004.5 | T6: -17895.5 | U6: {=IFERROR(_xlfn.IFS(tblPedidos[[#This Row],[estado_operativo]]="ENTREGADO",tblPedidos[[#This Row],[ganancia_calc]],tblPedidos[[#This Row],[estado_operativo]]="DEVOLUCION",tblPedidos[[#This Row],[costo_devolucion_estimado]]),0)} -> 0 | V6: 0 | W6: 59900 | X6: 17895.5 | Y6: 25000 | Z6: 46043 | AA6: 1 | AB6: 0.99861111 | AC6: PENDIENTE | AD6: PENDIENTE | AE6: PENDIENTE
C7: 1023 | D7: 63457261 | E7: 46043 | F7: Alexandra Hernández | G7: INTERRAPIDISIMO | J7: PENDIENTE | L7: CESAR | M7: LA LOMA | N7: La loma el paso, cesar. CR 13 # 16-05 | O7: 3126235411 | P7: {=IFERROR(_xlfn.XLOOKUP(tblPedidos[[#This Row],[id_dropi]],tblNotas[[#This Row],[id__dropi]],tblNotas[[#This Row],[Notas Manuales]], “”, 0),"")} | Q7: La loma el paso, cesar. CR 13 # 16 - 05. Barrio San Marcos. | R7: Cepillo Plancha Secador 2 en 1 Alisador x2 | S7: 27529.5 | T7: -18570.5 | U7: {=IFERROR(_xlfn.IFS(tblPedidos[[#This Row],[estado_operativo]]="ENTREGADO",tblPedidos[[#This Row],[ganancia_calc]],tblPedidos[[#This Row],[estado_operativo]]="DEVOLUCION",tblPedidos[[#This Row],[costo_devolucion_estimado]]),0)} -> 0 | V7: 0 | W7: 74900 | X7: 18570.5 | Y7: 28800 | Z7: 46043 | AA7: 1 | AB7: 0.95416667 | AC7: PENDIENTE | AD7: PENDIENTE | AE7: PENDIENTE
C8: 1024 | D8: 63457042 | E8: 46043 | F8: Herna Rivas | G8: ENVIA | J8: PENDIENTE | L8: VALLE | M8: BUGALAGRANDE | N8: Kr 5#3-84 Vuelta la virgen la María | O8: 3052542630 | P8: {=IFERROR(_xlfn.XLOOKUP(tblPedidos[[#This Row],[id_dropi]],tblNotas[[#This Row],[id__dropi]],tblNotas[[#This Row],[Notas Manuales]], “”, 0),"")} | Q8: Kr 5#3-84 Vuelta la virgen la María | R8: Cepillo Plancha Secador 2 en 1 Alisador x2 | S8: 25436.5 | T8: -12530.8 | U8: {=IFERROR(_xlfn.IFS(tblPedidos[[#This Row],[estado_operativo]]="ENTREGADO",tblPedidos[[#This Row],[ganancia_calc]],tblPedidos[[#This Row],[estado_operativo]]="DEVOLUCION",tblPedidos[[#This Row],[costo_devolucion_estimado]]),0)} -> 0 | V8: 0 | W8: 69900 | X8: 15663.5 | Y8: 28800 | Z8: 46043 | AA8: 1 | AB8: 0.95069444 | AC8: PENDIENTE | AD8: PENDIENTE | AE8: PENDIENTE
C9: 1021 | D9: 63456378 | E9: 46043 | F9: Miladys Arrieta | G9: INTERRAPIDISIMO | J9: PENDIENTE | L9: SUCRE | M9: SAN MARCOS | N9: OFICINA INTERRAPIDISIMO SAN MARCOS | O9: 3128625601 | P9: {=IFERROR(_xlfn.XLOOKUP(tblPedidos[[#This Row],[id_dropi]],tblNotas[[#This Row],[id__dropi]],tblNotas[[#This Row],[Notas Manuales]], “”, 0),"")} | Q9: CLIENTE RECLAMA EN OFICINA INTERRAPIDISIMO CARRERA 21 # 24A 44 SAN MARCOS SUCRE | R9: Cepillo Plancha Secador 2 en 1 Alisador x1 | S9: 16801 | T9: -18699 | U9: {=IFERROR(_xlfn.IFS(tblPedidos[[#This Row],[estado_operativo]]="ENTREGADO",tblPedidos[[#This Row],[ganancia_calc]],tblPedidos[[#This Row],[estado_operativo]]="DEVOLUCION",tblPedidos[[#This Row],[costo_devolucion_estimado]]),0)} -> 0 | V9: 0 | W9: 49900 | X9: 18699 | Y9: 14400 | Z9: 46043 | AA9: 1 | AB9: 0.94583333 | AC9: PENDIENTE | AD9: PENDIENTE | AE9: PENDIENTE
C10: 1018 | D10: 63455995 | E10: 46043 | F10: Yurany García | G10: INTERRAPIDISIMO | J10: PENDIENTE | L10: CUNDINAMARCA | M10: SOACHA | N10: OFICINA INTERRAPIDISIMO PRINCIPAL SOACHA | O10: 3214968096 | P10: {=IFERROR(_xlfn.XLOOKUP(tblPedidos[[#This Row],[id_dropi]],tblNotas[[#This Row],[id__dropi]],tblNotas[[#This Row],[Notas Manuales]], “”, 0),"")} | Q10: CLIENTE RECLAMA EN OFICINA INTERRAPIDISIMO PRINCIPAL SOACHA | R10: Cepillo Plancha Secador 2 en 1 Alisador x1 | S10: 28779.5 | T10: -11720.5 | U10: {=IFERROR(_xlfn.IFS(tblPedidos[[#This Row],[estado_operativo]]="ENTREGADO",tblPedidos[[#This Row],[ganancia_calc]],tblPedidos[[#This Row],[estado_operativo]]="DEVOLUCION",tblPedidos[[#This Row],[costo_devolucion_estimado]]),0)} -> 0 | V10: 0 | W10: 54900 | X10: 11720.5 | Y10: 14400 | Z10: 46043 | AA10: 1 | AB10: 0.94236111 | AC10: PENDIENTE | AD10: PENDIENTE | AE10: PENDIENTE
C11: 1019 | D11: 63455771 | E11: 46043 | F11: Mercedes Sepulveda | G11: INTERRAPIDISIMO | J11: PENDIENTE | L11: CUNDINAMARCA | M11: BOGOTA | N11: Calle 18 #4-51 | O11: 3125320701 | P11: {=IFERROR(_xlfn.XLOOKUP(tblPedidos[[#This Row],[id_dropi]],tblNotas[[#This Row],[id__dropi]],tblNotas[[#This Row],[Notas Manuales]], “”, 0),"")} | R11: Quemador de grasa Lemme Burn 60 cáps x2 | S11: 20654.5 | T11: -19245.5 | U11: {=IFERROR(_xlfn.IFS(tblPedidos[[#This Row],[estado_operativo]]="ENTREGADO",tblPedidos[[#This Row],[ganancia_calc]],tblPedidos[[#This Row],[estado_operativo]]="DEVOLUCION",tblPedidos[[#This Row],[costo_devolucion_estimado]]),0)} -> 0 | V11: 0 | W11: 89900 | X11: 19245.5 | Y11: 50000 | Z11: 46043 | AA11: 1 | AB11: 0.94097222 | AC11: PENDIENTE | AD11: PENDIENTE | AE11: PENDIENTE
C12: 1020 | D12: 63455714 | E12: 46043 | F12: Carmen Daniela Criollo Pacheco | G12: INTERRAPIDISIMO | J12: PENDIENTE | L12: ARAUCA | M12: SARAVENA | N12: Calle 7 #20-35 | O12: 3164638889 | P12: {=IFERROR(_xlfn.XLOOKUP(tblPedidos[[#This Row],[id_dropi]],tblNotas[[#This Row],[id__dropi]],tblNotas[[#This Row],[Notas Manuales]], “”, 0),"")} | R12: Cepillo Plancha Secador 2 en 1 Alisador x1 | S12: 16801 | T12: -18699 | U12: {=IFERROR(_xlfn.IFS(tblPedidos[[#This Row],[estado_operativo]]="ENTREGADO",tblPedidos[[#This Row],[ganancia_calc]],tblPedidos[[#This Row],[estado_operativo]]="DEVOLUCION",tblPedidos[[#This Row],[costo_devolucion_estimado]]),0)} -> 0 | V12: 0 | W12: 49900 | X12: 18699 | Y12: 14400 | Z12: 46043 | AA12: 1 | AB12: 0.94097222 | AC12: PENDIENTE | AD12: PENDIENTE | AE12: PENDIENTE
C13: 1029 | D13: 63455608 | E13: 46043 | F13: Nora Mosquera | G13: INTERRAPIDISIMO | J13: PENDIENTE | L13: CAUCA | M13: PUERTO TEJADA | N13: Cliente recoge pedido en oficina de Interrapidisimo en Puerto Tejada cliente recoge en esa oficina | O13: 3146569277 | P13: {=IFERROR(_xlfn.XLOOKUP(tblPedidos[[#This Row],[id_dropi]],tblNotas[[#This Row],[id__dropi]],tblNotas[[#This Row],[Notas Manuales]], “”, 0),"")} | Q13: PEDIDO PARA RECOGER EN OFICINA DE INTERRAPIDISIMO | R13: Aceite de Batana x2 | S13: 26779.5 | T13: -18120.5 | U13: {=IFERROR(_xlfn.IFS(tblPedidos[[#This Row],[estado_operativo]]="ENTREGADO",tblPedidos[[#This Row],[ganancia_calc]],tblPedidos[[#This Row],[estado_operativo]]="DEVOLUCION",tblPedidos[[#This Row],[costo_devolucion_estimado]]),0)} -> 0 | V13: 0 | W13: 64900 | X13: 18120.5 | Y13: 20000 | Z13: 46043 | AA13: 1 | AB13: 0.94027778 | AC13: PENDIENTE | AD13: PENDIENTE | AE13: PENDIENTE
C14: 1030 | D14: 63455546 | E14: 46043 | F14: Carmen Garcia | G14: ENVIA | J14: PENDIENTE | L14: VALLE | M14: CALI | N14: Calle 16 # 45 B bis - 23, Barrio Las Granjas | O14: 3172771840 | P14: {=IFERROR(_xlfn.XLOOKUP(tblPedidos[[#This Row],[id_dropi]],tblNotas[[#This Row],[id__dropi]],tblNotas[[#This Row],[Notas Manuales]], “”, 0),"")} | Q14: Barrio Las Granjas | R14: DUO capilar ADIOS FRIZZ - 500ml x1 | S14: 32946.5 | T14: -10802.8 | U14: {=IFERROR(_xlfn.IFS(tblPedidos[[#This Row],[estado_operativo]]="ENTREGADO",tblPedidos[[#This Row],[ganancia_calc]],tblPedidos[[#This Row],[estado_operativo]]="DEVOLUCION",tblPedidos[[#This Row],[costo_devolucion_estimado]]),0)} -> 0 | V14: 0 | W14: 69900 | X14: 13503.5 | Y14: 23450 | Z14: 46043 | AA14: 1 | AB14: 0.93958333 | AC14: PENDIENTE | AD14: PENDIENTE | AE14: PENDIENTE
C15: 1031 | D15: 63455526 | E15: 46043 | F15: Luisana Rojas | G15: INTERRAPIDISIMO | J15: PENDIENTE | L15: NORTE DE SANTANDER | M15: TIBU | N15: Cliente recoge pedido en oficina de Interrapidisimo en Tibu cliente recoge en esa oficina | O15: 3138816999 | P15: {=IFERROR(_xlfn.XLOOKUP(tblPedidos[[#This Row],[id_dropi]],tblNotas[[#This Row],[id__dropi]],tblNotas[[#This Row],[Notas Manuales]], “”, 0),"")} | Q15: PEDIDO PARA RECOGER EN OFICINA DE INTERRAPIDISIMO | R15: Quemador de grasa Lemme Burn 60 cáps x2 | S15: 20654.5 | T15: -19245.5 | U15: {=IFERROR(_xlfn.IFS(tblPedidos[[#This Row],[estado_operativo]]="ENTREGADO",tblPedidos[[#This Row],[ganancia_calc]],tblPedidos[[#This Row],[estado_operativo]]="DEVOLUCION",tblPedidos[[#This Row],[costo_devolucion_estimado]]),0)} -> 0 | V15: 0 | W15: 89900 | X15: 19245.5 | Y15: 50000 | Z15: 46043 | AA15: 1 | AB15: 0.93888889 | AC15: PENDIENTE | AD15: PENDIENTE | AE15: PENDIENTE
C16: 1028 | D16: 63455501 | E16: 46043 | F16: Marisol Ospina Cortes | G16: INTERRAPIDISIMO | J16: PENDIENTE | L16: CUNDINAMARCA | M16: BOGOTA | N16: Cr 79h N 57g 93 sur, Barrio Porvenir Roma, Kenedy | O16: 3018109025 | P16: {=IFERROR(_xlfn.XLOOKUP(tblPedidos[[#This Row],[id_dropi]],tblNotas[[#This Row],[id__dropi]],tblNotas[[#This Row],[Notas Manuales]], “”, 0),"")} | Q16: Cr 79h N 57g 93 sur, Barrio Porvenir Roma, Kenedy - Casa esquinera | R16: Cepillo Plancha Secador 2 en 1 Alisador x1 | S16: 28779.5 | T16: -11720.5 | U16: {=IFERROR(_xlfn.IFS(tblPedidos[[#This Row],[estado_operativo]]="ENTREGADO",tblPedidos[[#This Row],[ganancia_calc]],tblPedidos[[#This Row],[estado_operativo]]="DEVOLUCION",tblPedidos[[#This Row],[costo_devolucion_estimado]]),0)} -> 0 | V16: 0 | W16: 54900 | X16: 11720.5 | Y16: 14400 | Z16: 46043 | AA16: 1 | AB16: 0.93888889 | AC16: PENDIENTE | AD16: PENDIENTE | AE16: PENDIENTE
C17: 1025 | D17: 63455497 | E17: 46043 | F17: Leidy Zúñiga | G17: INTERRAPIDISIMO | J17: PENDIENTE | L17: TOLIMA | M17: ROVIRA | N17: Cliente recoge pedido en oficina de Interrapidisimo en Rovira cliente recoge en esa oficina | O17: 3115222104 | P17: {=IFERROR(_xlfn.XLOOKUP(tblPedidos[[#This Row],[id_dropi]],tblNotas[[#This Row],[id__dropi]],tblNotas[[#This Row],[Notas Manuales]], “”, 0),"")} | Q17: PEDIDO PARA RECOGER EN OFICINA DE INTERRAPIDISIMO | R17: Quemador de grasa Lemme Burn 60 cáps x2 | S17: 20654.5 | T17: -19245.5 | U17: {=IFERROR(_xlfn.IFS(tblPedidos[[#This Row],[estado_operativo]]="ENTREGADO",tblPedidos[[#This Row],[ganancia_calc]],tblPedidos[[#This Row],[estado_operativo]]="DEVOLUCION",tblPedidos[[#This Row],[costo_devolucion_estimado]]),0)} -> 0 | V17: 0 | W17: 89900 | X17: 19245.5 | Y17: 50000 | Z17: 46043 | AA17: 1 | AB17: 0.93888889 | AC17: PENDIENTE | AD17: PENDIENTE | AE17: PENDIENTE
C18: 1026 | D18: 63455476 | E18: 46043 | F18: Luz Dueñas | G18: INTERRAPIDISIMO | J18: PENDIENTE | L18: CUNDINAMARCA | M18: BOGOTA | N18: Transversal 59 N 74 58 sur, barrio Sierra Morena | O18: 3227178119 | P18: {=IFERROR(_xlfn.XLOOKUP(tblPedidos[[#This Row],[id_dropi]],tblNotas[[#This Row],[id__dropi]],tblNotas[[#This Row],[Notas Manuales]], “”, 0),"")} | R18: Quemador de grasa Lemme Burn 60 cáps x2 | S18: 20654.5 | T18: -19245.5 | U18: {=IFERROR(_xlfn.IFS(tblPedidos[[#This Row],[estado_operativo]]="ENTREGADO",tblPedidos[[#This Row],[ganancia_calc]],tblPedidos[[#This Row],[estado_operativo]]="DEVOLUCION",tblPedidos[[#This Row],[costo_devolucion_estimado]]),0)} -> 0 | V18: 0 | W18: 89900 | X18: 19245.5 | Y18: 50000 | Z18: 46043 | AA18: 1 | AB18: 0.93819444 | AC18: PENDIENTE | AD18: PENDIENTE | AE18: PENDIENTE
C19: 1027 | D19: 63455447 | E19: 46043 | F19: Carolina Hurtado | G19: INTERRAPIDISIMO | J19: PENDIENTE | L19: VALLE | M19: CALI | N19: CLIENTE RECOGE EN OFICINA INTERRAPIDISIMO Cra. 15 #33b-09, Comuna 8, | O19: 3177584912 | P19: {=IFERROR(_xlfn.XLOOKUP(tblPedidos[[#This Row],[id_dropi]],tblNotas[[#This Row],[id__dropi]],tblNotas[[#This Row],[Notas Manuales]], “”, 0),"")} | Q19: PERMITIR QUE EL CLIENTE REVISE EL PEDIDO ANTES DE PAGAR | R19: Quemador de grasa Lemme Burn 60 cáps x1 | S19: 18179.5 | T19: -11720.5 | U19: {=IFERROR(_xlfn.IFS(tblPedidos[[#This Row],[estado_operativo]]="ENTREGADO",tblPedidos[[#This Row],[ganancia_calc]],tblPedidos[[#This Row],[estado_operativo]]="DEVOLUCION",tblPedidos[[#This Row],[costo_devolucion_estimado]]),0)} -> 0 | V19: 0 | W19: 54900 | X19: 11720.5 | Y19: 25000 | Z19: 46043 | AA19: 1 | AB19: 0.9375 | AC19: PENDIENTE | AD19: PENDIENTE | AE19: PENDIENTE
C20: 1017 | D20: 63455323 | E20: 46043 | F20: Brenda Valencia | G20: INTERRAPIDISIMO | J20: PENDIENTE | L20: NARIÑO | M20: TUMACO | N20: OFICINA INTERRAPIDISIMO TUMACO | O20: 3241743932 | P20: {=IFERROR(_xlfn.XLOOKUP(tblPedidos[[#This Row],[id_dropi]],tblNotas[[#This Row],[id__dropi]],tblNotas[[#This Row],[Notas Manuales]], “”, 0),"")} | Q20: CLIENTE RECLAMA EN OFICINA INTERRAPIDISIMO TUMACO | R20: Cepillo Plancha Secador 2 en 1 Alisador x1 | S20: 22829.5 | T20: -17670.5 | U20: {=IFERROR(_xlfn.IFS(tblPedidos[[#This Row],[estado_operativo]]="ENTREGADO",tblPedidos[[#This Row],[ganancia_calc]],tblPedidos[[#This Row],[estado_operativo]]="DEVOLUCION",tblPedidos[[#This Row],[costo_devolucion_estimado]]),0)} -> 0 | V20: 0 | W20: 54900 | X20: 17670.5 | Y20: 14400 | Z20: 46043 | AA20: 1 | AB20: 0.93680556 | AC20: PENDIENTE | AD20: PENDIENTE | AE20: PENDIENTE
C21: 1007 | D21: 63455271 | E21: 46043 | F21: Nancy Cruz | G21: INTERRAPIDISIMO | J21: PENDIENTE | L21: RISARALDA | M21: PEREIRA | N21: Manzana 9 casa 15 piso 2 Barrio perla del Sur | O21: 3014683522 | P21: {=IFERROR(_xlfn.XLOOKUP(tblPedidos[[#This Row],[id_dropi]],tblNotas[[#This Row],[id__dropi]],tblNotas[[#This Row],[Notas Manuales]], “”, 0),"")} | Q21: Barrio perla del Sur | R21: DUO capilar ADIOS FRIZZ - 500ml x1 | S21: 34054.5 | T21: -12395.5 | U21: {=IFERROR(_xlfn.IFS(tblPedidos[[#This Row],[estado_operativo]]="ENTREGADO",tblPedidos[[#This Row],[ganancia_calc]],tblPedidos[[#This Row],[estado_operativo]]="DEVOLUCION",tblPedidos[[#This Row],[costo_devolucion_estimado]]),0)} -> 0 | V21: 0 | W21: 69900 | X21: 12395.5 | Y21: 23450 | Z21: 46043 | AA21: 1 | AB21: 0.93680556 | AC21: PENDIENTE | AD21: PENDIENTE | AE21: PENDIENTE
C22: 1008 | D22: 63455085 | E22: 46043 | F22: Geidis Araujo | G22: INTERRAPIDISIMO | J22: PENDIENTE | L22: ATLANTICO | M22: SABANALARGA | N22: OFICINA INTERRAPIDISIMO SABANALARGA | O22: 3116626088 | P22: {=IFERROR(_xlfn.XLOOKUP(tblPedidos[[#This Row],[id_dropi]],tblNotas[[#This Row],[id__dropi]],tblNotas[[#This Row],[Notas Manuales]], “”, 0),"")} | Q22: CLIENTE RECLAMA EN OFICINA INTERRAPIDISIMO SABANALARGA | R22: Cepillo Plancha Secador 2 en 1 Alisador x2 | S22: 27529.5 | T22: -18570.5 | U22: {=IFERROR(_xlfn.IFS(tblPedidos[[#This Row],[estado_operativo]]="ENTREGADO",tblPedidos[[#This Row],[ganancia_calc]],tblPedidos[[#This Row],[estado_operativo]]="DEVOLUCION",tblPedidos[[#This Row],[costo_devolucion_estimado]]),0)} -> 0 | V22: 0 | W22: 74900 | X22: 18570.5 | Y22: 28800 | Z22: 46043 | AA22: 1 | AB22: 0.93541667 | AC22: PENDIENTE | AD22: PENDIENTE | AE22: PENDIENTE
C23: 1009 | D23: 63454946 | E23: 46043 | F23: Lyda Guzmán | G23: INTERRAPIDISIMO | J23: PENDIENTE | L23: CUNDINAMARCA | M23: BOGOTA | N23: Cra 71b bis # 12-30 torre 1 apto 203 Conj Recodo de Alsacia, Ciudad Alsacia la nueva | O23: 3125652470 | P23: {=IFERROR(_xlfn.XLOOKUP(tblPedidos[[#This Row],[id_dropi]],tblNotas[[#This Row],[id__dropi]],tblNotas[[#This Row],[Notas Manuales]], “”, 0),"")} | Q23: Conjunto Recodo de Alsacia, Ciudad Alsacia la nueva | R23: DUO capilar ADIOS FRIZZ - 500ml x1 | S23: 28104.5 | T23: -18345.5 | U23: {=IFERROR(_xlfn.IFS(tblPedidos[[#This Row],[estado_operativo]]="ENTREGADO",tblPedidos[[#This Row],[ganancia_calc]],tblPedidos[[#This Row],[estado_operativo]]="DEVOLUCION",tblPedidos[[#This Row],[costo_devolucion_estimado]]),0)} -> 0 | V23: 0 | W23: 69900 | X23: 18345.5 | Y23: 23450 | Z23: 46043 | AA23: 1 | AB23: 0.93472222 | AC23: PENDIENTE | AD23: PENDIENTE | AE23: PENDIENTE
C24: 1006 | D24: 63454914 | E24: 46043 | F24: Rosita Palacios | G24: INTERRAPIDISIMO | J24: PENDIENTE | L24: PUTUMAYO | M24: PUERTO CAICEDO | N24: Cliente recoge pedido en oficina de Interrapidisimo en Puerto Caicedo cliente recoge en esa oficina | O24: 3219523165 | P24: {=IFERROR(_xlfn.XLOOKUP(tblPedidos[[#This Row],[id_dropi]],tblNotas[[#This Row],[id__dropi]],tblNotas[[#This Row],[Notas Manuales]], “”, 0),"")} | Q24: PEDIDO PARA RECOGER EN OFICINA DE INTERRAPIDISIMO | R24: Quemador de grasa Lemme Burn 60 cáps x2 | S24: 20654.5 | T24: -19245.5 | U24: {=IFERROR(_xlfn.IFS(tblPedidos[[#This Row],[estado_operativo]]="ENTREGADO",tblPedidos[[#This Row],[ganancia_calc]],tblPedidos[[#This Row],[estado_operativo]]="DEVOLUCION",tblPedidos[[#This Row],[costo_devolucion_estimado]]),0)} -> 0 | V24: 0 | W24: 89900 | X24: 19245.5 | Y24: 50000 | Z24: 46043 | AA24: 1 | AB24: 0.93402778 | AC24: PENDIENTE | AD24: PENDIENTE | AE24: PENDIENTE
C25: 1003 | D25: 63454816 | E25: 46043 | F25: MONICA ASTRITH JAIME | G25: INTERRAPIDISIMO | J25: PENDIENTE | L25: NORTE DE SANTANDER | M25: ABREGO | N25: CARRERA 3 #15-21. A BARRIO SAN CARLOS. | O25: 3133586050 | P25: {=IFERROR(_xlfn.XLOOKUP(tblPedidos[[#This Row],[id_dropi]],tblNotas[[#This Row],[id__dropi]],tblNotas[[#This Row],[Notas Manuales]], “”, 0),"")} | R25: Quemador de grasa Lemme Burn 60 cáps x2 | S25: 15879.5 | T25: -19020.5 | U25: {=IFERROR(_xlfn.IFS(tblPedidos[[#This Row],[estado_operativo]]="ENTREGADO",tblPedidos[[#This Row],[ganancia_calc]],tblPedidos[[#This Row],[estado_operativo]]="DEVOLUCION",tblPedidos[[#This Row],[costo_devolucion_estimado]]),0)} -> 0 | V25: 0 | W25: 84900 | X25: 19020.5 | Y25: 50000 | Z25: 46043 | AA25: 1 | AB25: 0.93402778 | AC25: PENDIENTE | AD25: PENDIENTE | AE25: PENDIENTE
C26: 1004 | D26: 63454680 | E26: 46043 | F26: Katy Yulieth Romero Luna | G26: INTERRAPIDISIMO | J26: PENDIENTE | L26: SUCRE | M26: SAN MARCOS | N26: 𝒄𝒂𝒍𝒍𝒆 23 𝒄𝒂𝒓𝒆𝒓𝒂 35 𝒏.𝒂7.𝒃 𝒑𝒖𝒆𝒓𝒕𝒐 𝒍𝒐𝒑𝒆𝒛 | O26: 3246209286 | P26: {=IFERROR(_xlfn.XLOOKUP(tblPedidos[[#This Row],[id_dropi]],tblNotas[[#This Row],[id__dropi]],tblNotas[[#This Row],[Notas Manuales]], “”, 0),"")} | R26: Cepillo Plancha Secador 2 en 1 Alisador x2 | S26: 27529.5 | T26: -18570.5 | U26: {=IFERROR(_xlfn.IFS(tblPedidos[[#This Row],[estado_operativo]]="ENTREGADO",tblPedidos[[#This Row],[ganancia_calc]],tblPedidos[[#This Row],[estado_operativo]]="DEVOLUCION",tblPedidos[[#This Row],[costo_devolucion_estimado]]),0)} -> 0 | V26: 0 | W26: 74900 | X26: 18570.5 | Y26: 28800 | Z26: 46043 | AA26: 1 | AB26: 0.93263889 | AC26: PENDIENTE | AD26: PENDIENTE | AE26: PENDIENTE
C27: 1005 | D27: 63454655 | E27: 46043 | F27: Ester Julia Nazarit | G27: INTERRAPIDISIMO | J27: PENDIENTE | L27: CAUCA | M27: SANTANDER DE QUILICHAO | N27: Carrera 19 #2-72 barrio porvenir. | O27: 3216764581 | P27: {=IFERROR(_xlfn.XLOOKUP(tblPedidos[[#This Row],[id_dropi]],tblNotas[[#This Row],[id__dropi]],tblNotas[[#This Row],[Notas Manuales]], “”, 0),"")} | R27: Aceite de Batana x4 | S27: 35429.5 | T27: -19470.5 | U27: {=IFERROR(_xlfn.IFS(tblPedidos[[#This Row],[estado_operativo]]="ENTREGADO",tblPedidos[[#This Row],[ganancia_calc]],tblPedidos[[#This Row],[estado_operativo]]="DEVOLUCION",tblPedidos[[#This Row],[costo_devolucion_estimado]]),0)} -> 0 | V27: 0 | W27: 94900 | X27: 19470.5 | Y27: 40000 | Z27: 46043 | AA27: 1 | AB27: 0.93263889 | AC27: PENDIENTE | AD27: PENDIENTE | AE27: PENDIENTE
C28: 1014 | D28: 63454646 | E28: 46043 | F28: Milagro Pallares | G28: INTERRAPIDISIMO | J28: PENDIENTE | L28: ATLANTICO | M28: MALAMBO | N28: Calle 5 # 17 - 03 Barrio Abajo | O28: 3115287480 | P28: {=IFERROR(_xlfn.XLOOKUP(tblPedidos[[#This Row],[id_dropi]],tblNotas[[#This Row],[id__dropi]],tblNotas[[#This Row],[Notas Manuales]], “”, 0),"")} | Q28: Barrio Abajo | R28: DUO capilar ADIOS FRIZZ - 300 ml x1 | S28: 22054.5 | T28: -17895.5 | U28: {=IFERROR(_xlfn.IFS(tblPedidos[[#This Row],[estado_operativo]]="ENTREGADO",tblPedidos[[#This Row],[ganancia_calc]],tblPedidos[[#This Row],[estado_operativo]]="DEVOLUCION",tblPedidos[[#This Row],[costo_devolucion_estimado]]),0)} -> 0 | V28: 0 | W28: 59900 | X28: 17895.5 | Y28: 19950 | Z28: 46043 | AA28: 1 | AB28: 0.93263889 | AC28: PENDIENTE | AD28: PENDIENTE | AE28: PENDIENTE
C29: 1015 | D29: 63454453 | E29: 46043 | F29: Nidia Perdomo | G29: INTERRAPIDISIMO | J29: PENDIENTE | L29: TOLIMA | M29: IBAGUE | N29: Manzana C - casa #15 Barrio San Antonio | O29: 3228781846 | P29: {=IFERROR(_xlfn.XLOOKUP(tblPedidos[[#This Row],[id_dropi]],tblNotas[[#This Row],[id__dropi]],tblNotas[[#This Row],[Notas Manuales]], “”, 0),"")} | Q29: Manzana C - casa 15 Barrio San Antonio | R29: DUO capilar ADIOS FRIZZ - 500ml x1 | S29: 30551 | T29: -15899 | U29: {=IFERROR(_xlfn.IFS(tblPedidos[[#This Row],[estado_operativo]]="ENTREGADO",tblPedidos[[#This Row],[ganancia_calc]],tblPedidos[[#This Row],[estado_operativo]]="DEVOLUCION",tblPedidos[[#This Row],[costo_devolucion_estimado]]),0)} -> 0 | V29: 0 | W29: 69900 | X29: 15899 | Y29: 23450 | Z29: 46043 | AA29: 1 | AB29: 0.93055556 | AC29: PENDIENTE | AD29: PENDIENTE | AE29: PENDIENTE
C30: 1016 | D30: 63454427 | E30: 46043 | F30: Diana Ochoa | G30: INTERRAPIDISIMO | J30: PENDIENTE | L30: BOYACA | M30: TUNJA | N30: Carrera 10 #64 b 79 apto 202 torre 30, Parque residencial el refugio | O30: 3115127049 | P30: {=IFERROR(_xlfn.XLOOKUP(tblPedidos[[#This Row],[id_dropi]],tblNotas[[#This Row],[id__dropi]],tblNotas[[#This Row],[Notas Manuales]], “”, 0),"")} | R30: Quemador de grasa Lemme Burn 60 cáps x2 | S30: 15879.5 | T30: -19020.5 | U30: {=IFERROR(_xlfn.IFS(tblPedidos[[#This Row],[estado_operativo]]="ENTREGADO",tblPedidos[[#This Row],[ganancia_calc]],tblPedidos[[#This Row],[estado_operativo]]="DEVOLUCION",tblPedidos[[#This Row],[costo_devolucion_estimado]]),0)} -> 0 | V30: 0 | W30: 84900 | X30: 19020.5 | Y30: 50000 | Z30: 46043 | AA30: 1 | AB30: 0.93055556 | AC30: PENDIENTE | AD30: PENDIENTE | AE30: PENDIENTE
C31: 1013 | D31: 63454372 | E31: 46043 | F31: Liliana Duran | G31: INTERRAPIDISIMO | J31: PENDIENTE | L31: NORTE DE SANTANDER | M31: TEORAMA | N31: CLIENTE RECOGE EN OFICINA INTERRAPIDISIMO Calle 4 #8-29 ofc 3550 | O31: 3235242496 | P31: {=IFERROR(_xlfn.XLOOKUP(tblPedidos[[#This Row],[id_dropi]],tblNotas[[#This Row],[id__dropi]],tblNotas[[#This Row],[Notas Manuales]], “”, 0),"")} | Q31: PEDIDO PARA RECOGER EN OFICINA DE INTERRAPIDISIMO | R31: Truly Soft Serve + T. Glazed Donut 60ml x1 | S31: 26554.5 | T31: -18345.5 | U31: {=IFERROR(_xlfn.IFS(tblPedidos[[#This Row],[estado_operativo]]="ENTREGADO",tblPedidos[[#This Row],[ganancia_calc]],tblPedidos[[#This Row],[estado_operativo]]="DEVOLUCION",tblPedidos[[#This Row],[costo_devolucion_estimado]]),0)} -> 0 | V31: 0 | W31: 69900 | X31: 18345.5 | Y31: 25000 | Z31: 46043 | AA31: 1 | AB31: 0.92986111 | AC31: PENDIENTE | AD31: PENDIENTE | AE31: PENDIENTE
C32: 1010 | D32: 63454221 | E32: 46043 | F32: Nancy María Vélez | G32: ENVIA | J32: PENDIENTE | L32: ANTIOQUIA | M32: BELLO | N32: Diagonal 53 #42-71 Niquia | O32: 3122842049 | P32: {=IFERROR(_xlfn.XLOOKUP(tblPedidos[[#This Row],[id_dropi]],tblNotas[[#This Row],[id__dropi]],tblNotas[[#This Row],[Notas Manuales]], “”, 0),"")} | R32: Truly Soft Serve + T. Glazed Donut 60ml x1 | S32: 29236.5 | T32: -12530.8 | U32: {=IFERROR(_xlfn.IFS(tblPedidos[[#This Row],[estado_operativo]]="ENTREGADO",tblPedidos[[#This Row],[ganancia_calc]],tblPedidos[[#This Row],[estado_operativo]]="DEVOLUCION",tblPedidos[[#This Row],[costo_devolucion_estimado]]),0)} -> 0 | V32: 0 | W32: 69900 | X32: 15663.5 | Y32: 25000 | Z32: 46043 | AA32: 1 | AB32: 0.92916667 | AC32: PENDIENTE | AD32: PENDIENTE | AE32: PENDIENTE
C33: 1011 | D33: 63454140 | E33: 46043 | F33: Wilerma Ruiz | G33: INTERRAPIDISIMO | J33: PENDIENTE | L33: BOYACA | M33: SACHICA | N33: Calle 3 # 1 - 21 centro sachica | O33: 3217320042 | P33: {=IFERROR(_xlfn.XLOOKUP(tblPedidos[[#This Row],[id_dropi]],tblNotas[[#This Row],[id__dropi]],tblNotas[[#This Row],[Notas Manuales]], “”, 0),"")} | R33: Cepillo Plancha Secador 2 en 1 Alisador x2 | S33: 22754.5 | T33: -18345.5 | U33: {=IFERROR(_xlfn.IFS(tblPedidos[[#This Row],[estado_operativo]]="ENTREGADO",tblPedidos[[#This Row],[ganancia_calc]],tblPedidos[[#This Row],[estado_operativo]]="DEVOLUCION",tblPedidos[[#This Row],[costo_devolucion_estimado]]),0)} -> 0 | V33: 0 | W33: 69900 | X33: 18345.5 | Y33: 28800 | Z33: 46043 | AA33: 1 | AB33: 0.92847222 | AC33: PENDIENTE | AD33: PENDIENTE | AE33: PENDIENTE
C34: 1012 | D34: 63454064 | E34: 46043 | F34: Eloísa del Carmen Andueza Burgos | G34: INTERRAPIDISIMO | J34: PENDIENTE | L34: CASANARE | M34: YOPAL | N34: Cliente recoge pedido en oficina de Interrapidisimo en Yopal cliente recoge en esa oficina | O34: 3227649115 | P34: {=IFERROR(_xlfn.XLOOKUP(tblPedidos[[#This Row],[id_dropi]],tblNotas[[#This Row],[id__dropi]],tblNotas[[#This Row],[Notas Manuales]], “”, 0),"")} | Q34: PEDIDO PARA RECOGER EN OFICINA DE INTERRAPIDISIMO | R34: Serum despigmentante SMOOTH LEGEND 60ml x1 | S34: 24004.5 | T34: -17895.5 | U34: {=IFERROR(_xlfn.IFS(tblPedidos[[#This Row],[estado_operativo]]="ENTREGADO",tblPedidos[[#This Row],[ganancia_calc]],tblPedidos[[#This Row],[estado_operativo]]="DEVOLUCION",tblPedidos[[#This Row],[costo_devolucion_estimado]]),0)} -> 0 | V34: 0 | W34: 59900 | X34: 17895.5 | Y34: 18000 | Z34: 46043 | AA34: 1 | AB34: 0.92777778 | AC34: PENDIENTE | AD34: PENDIENTE | AE34: PENDIENTE
C35: 1051 | D35: 63453464 | E35: 46043 | F35: Martin Eduardo Potes | G35: INTERRAPIDISIMO | J35: PENDIENTE | L35: ATLANTICO | M35: JUAN DE ACOSTA | N35: OFICINA INTERRAPIDISIMO JUAN DE ACOSTA | O35: 3008937303 | P35: {=IFERROR(_xlfn.XLOOKUP(tblPedidos[[#This Row],[id_dropi]],tblNotas[[#This Row],[id__dropi]],tblNotas[[#This Row],[Notas Manuales]], “”, 0),"")} | Q35: CLIENTE RECLAMA EN OFICINA DE INTERRAPIDISIMO JUAN DE ACOSTA. | R35: Bee Venom BSWELL x1 + Beevana crema +Varicose veins x2 | S35: 24879.5 | T35: -19020.5 | U35: {=IFERROR(_xlfn.IFS(tblPedidos[[#This Row],[estado_operativo]]="ENTREGADO",tblPedidos[[#This Row],[ganancia_calc]],tblPedidos[[#This Row],[estado_operativo]]="DEVOLUCION",tblPedidos[[#This Row],[costo_devolucion_estimado]]),0)} -> 0 | V35: 0 | W35: 84900 | X35: 19020.5 | Y35: 41000 | Z35: 46043 | AA35: 1 | AB35: 0.92361111 | AC35: PENDIENTE | AD35: PENDIENTE | AE35: PENDIENTE
C36: 1052 | D36: 63453457 | E36: 46043 | F36: María Dihanora Cárdenas | G36: INTERRAPIDISIMO | J36: PENDIENTE | L36: PUTUMAYO | M36: VILLAGARZON | N36: Cliente recoge pedido en oficina de Interrapidisimo en Villagarzon cliente recoge en esa oficina | O36: 3503802979 | P36: {=IFERROR(_xlfn.XLOOKUP(tblPedidos[[#This Row],[id_dropi]],tblNotas[[#This Row],[id__dropi]],tblNotas[[#This Row],[Notas Manuales]], “”, 0),"")} | Q36: PEDIDO PARA RECOGER EN OFICINA DE INTERRAPIDISIMO | R36: DUO capilar ADIOS FRIZZ - 500ml x2 | S36: 42854.5 | T36: -20145.5 | U36: {=IFERROR(_xlfn.IFS(tblPedidos[[#This Row],[estado_operativo]]="ENTREGADO",tblPedidos[[#This Row],[ganancia_calc]],tblPedidos[[#This Row],[estado_operativo]]="DEVOLUCION",tblPedidos[[#This Row],[costo_devolucion_estimado]]),0)} -> 0 | V36: 0 | W36: 109900 | X36: 20145.5 | Y36: 46900 | Z36: 46043 | AA36: 1 | AB36: 0.92361111 | AC36: PENDIENTE | AD36: PENDIENTE | AE36: PENDIENTE
C37: 1053 | D37: 63453247 | E37: 46043 | F37: Sandra Lozano | G37: INTERRAPIDISIMO | J37: PENDIENTE | L37: CASANARE | M37: VILLANUEVA (C) | N37: Cliente recoge pedido en oficina de Interrapidisimo en Villanueva (c) cliente recoge en esa oficina | O37: 3132166337 | P37: {=IFERROR(_xlfn.XLOOKUP(tblPedidos[[#This Row],[id_dropi]],tblNotas[[#This Row],[id__dropi]],tblNotas[[#This Row],[Notas Manuales]], “”, 0),"")} | Q37: PEDIDO PARA RECOGER EN OFICINA DE INTERRAPIDISIMO | R37: Quemador de grasa Lemme Burn 60 cáps x2 | S37: 20654.5 | T37: -19245.5 | U37: {=IFERROR(_xlfn.IFS(tblPedidos[[#This Row],[estado_operativo]]="ENTREGADO",tblPedidos[[#This Row],[ganancia_calc]],tblPedidos[[#This Row],[estado_operativo]]="DEVOLUCION",tblPedidos[[#This Row],[costo_devolucion_estimado]]),0)} -> 0 | V37: 0 | W37: 89900 | X37: 19245.5 | Y37: 50000 | Z37: 46043 | AA37: 1 | AB37: 0.92152778 | AC37: PENDIENTE | AD37: PENDIENTE | AE37: PENDIENTE
C38: 1050 | D38: 63452706 | E38: 46043 | F38: María Avila | G38: INTERRAPIDISIMO | J38: PENDIENTE | L38: CUNDINAMARCA | M38: BOGOTA | N38: Cra 9 # 81-85 sur | O38: 3133600679 | P38: {=IFERROR(_xlfn.XLOOKUP(tblPedidos[[#This Row],[id_dropi]],tblNotas[[#This Row],[id__dropi]],tblNotas[[#This Row],[Notas Manuales]], “”, 0),"")} | R38: Quemador de grasa Lemme Burn 60 cáps x2 | S38: 20654.5 | T38: -19245.5 | U38: {=IFERROR(_xlfn.IFS(tblPedidos[[#This Row],[estado_operativo]]="ENTREGADO",tblPedidos[[#This Row],[ganancia_calc]],tblPedidos[[#This Row],[estado_operativo]]="DEVOLUCION",tblPedidos[[#This Row],[costo_devolucion_estimado]]),0)} -> 0 | V38: 0 | W38: 89900 | X38: 19245.5 | Y38: 50000 | Z38: 46043 | AA38: 1 | AB38: 0.91805556 | AC38: PENDIENTE | AD38: PENDIENTE | AE38: PENDIENTE
C39: 1047 | D39: 63452558 | E39: 46043 | F39: Rafaél Varon Gámez | G39: INTERRAPIDISIMO | J39: PENDIENTE | L39: CUNDINAMARCA | M39: GIRARDOT | N39: Manzana 77 casa 15 barrio Kennedy | O39: 3153302201 | P39: {=IFERROR(_xlfn.XLOOKUP(tblPedidos[[#This Row],[id_dropi]],tblNotas[[#This Row],[id__dropi]],tblNotas[[#This Row],[Notas Manuales]], “”, 0),"")} | R39: Quemador de grasa Lemme Burn 60 cáps x2 | S39: 20654.5 | T39: -19245.5 | U39: {=IFERROR(_xlfn.IFS(tblPedidos[[#This Row],[estado_operativo]]="ENTREGADO",tblPedidos[[#This Row],[ganancia_calc]],tblPedidos[[#This Row],[estado_operativo]]="DEVOLUCION",tblPedidos[[#This Row],[costo_devolucion_estimado]]),0)} -> 0 | V39: 0 | W39: 89900 | X39: 19245.5 | Y39: 50000 | Z39: 46043 | AA39: 1 | AB39: 0.91736111 | AC39: PENDIENTE | AD39: PENDIENTE | AE39: PENDIENTE
C40: 1048 | D40: 63452433 | E40: 46043 | F40: maria yoleida banguera | G40: INTERRAPIDISIMO | J40: PENDIENTE | L40: CAUCA | M40: PUERTO TEJADA | N40: Carrera11 calle #18 - 02 barrio la cabaña | O40: 3225236597 | P40: {=IFERROR(_xlfn.XLOOKUP(tblPedidos[[#This Row],[id_dropi]],tblNotas[[#This Row],[id__dropi]],tblNotas[[#This Row],[Notas Manuales]], “”, 0),"")} | R40: Bee Venom BSWELL x1 + Beevana crema +Varicose veins x1 | S40: 17004.5 | T40: -17895.5 | U40: {=IFERROR(_xlfn.IFS(tblPedidos[[#This Row],[estado_operativo]]="ENTREGADO",tblPedidos[[#This Row],[ganancia_calc]],tblPedidos[[#This Row],[estado_operativo]]="DEVOLUCION",tblPedidos[[#This Row],[costo_devolucion_estimado]]),0)} -> 0 | V40: 0 | W40: 59900 | X40: 17895.5 | Y40: 25000 | Z40: 46043 | AA40: 1 | AB40: 0.91597222 | AC40: PENDIENTE | AD40: PENDIENTE | AE40: PENDIENTE
C41: 1049 | D41: 63452399 | E41: 46043 | F41: Coraima Valdez | G41: ENVIA | J41: PENDIENTE | L41: VALLE | M41: BUENAVENTURA | N41: Calle 4 #33B-12 INT 3 SAN FRANCISCO DE ASÍS | O41: 3152035188 | P41: {=IFERROR(_xlfn.XLOOKUP(tblPedidos[[#This Row],[id_dropi]],tblNotas[[#This Row],[id__dropi]],tblNotas[[#This Row],[Notas Manuales]], “”, 0),"")} | R41: Quemador de grasa Lemme Burn 60 cáps x3 | S41: 38696.5 | T41: -12962.8 | U41: {=IFERROR(_xlfn.IFS(tblPedidos[[#This Row],[estado_operativo]]="ENTREGADO",tblPedidos[[#This Row],[ganancia_calc]],tblPedidos[[#This Row],[estado_operativo]]="DEVOLUCION",tblPedidos[[#This Row],[costo_devolucion_estimado]]),0)} -> 0 | V41: 0 | W41: 129900 | X41: 16203.5 | Y41: 75000 | Z41: 46043 | AA41: 1 | AB41: 0.91527778 | AC41: PENDIENTE | AD41: PENDIENTE | AE41: PENDIENTE
C42: 1058 | D42: 63452328 | E42: 46043 | F42: Edith Obrian vasquez | G42: INTERRAPIDISIMO | J42: PENDIENTE | L42: BOLIVAR | M42: MARIA LA BAJA B | N42: INTERRAPIDISIMO MARIA LA BAJA CALLE CENTRAL | O42: 3225751581 | P42: {=IFERROR(_xlfn.XLOOKUP(tblPedidos[[#This Row],[id_dropi]],tblNotas[[#This Row],[id__dropi]],tblNotas[[#This Row],[Notas Manuales]], “”, 0),"")} | Q42: CLIENTE RECLAMA EN OFICINA DE MARIA LA BAJA CALLE CENTRAL | R42: Bee Venom BSWELL x1 + Beevana crema +Varicose veins x1 | S42: 17004.5 | T42: -17895.5 | U42: {=IFERROR(_xlfn.IFS(tblPedidos[[#This Row],[estado_operativo]]="ENTREGADO",tblPedidos[[#This Row],[ganancia_calc]],tblPedidos[[#This Row],[estado_operativo]]="DEVOLUCION",tblPedidos[[#This Row],[costo_devolucion_estimado]]),0)} -> 0 | V42: 0 | W42: 59900 | X42: 17895.5 | Y42: 25000 | Z42: 46043 | AA42: 1 | AB42: 0.91458333 | AC42: PENDIENTE | AD42: PENDIENTE | AE42: PENDIENTE
C43: 1059 | D43: 63452325 | E43: 46043 | F43: Sara Granados | G43: INTERRAPIDISIMO | J43: PENDIENTE | L43: CUNDINAMARCA | M43: BOGOTA | N43: Carrera 28d5 #123-48 barrio potrero grande diagonal a pisamos tres | O43: 3239498308 | P43: {=IFERROR(_xlfn.XLOOKUP(tblPedidos[[#This Row],[id_dropi]],tblNotas[[#This Row],[id__dropi]],tblNotas[[#This Row],[Notas Manuales]], “”, 0),"")} | R43: Quemador de grasa Lemme Burn 60 cáps x2 | S43: 15879.5 | T43: -19020.5 | U43: {=IFERROR(_xlfn.IFS(tblPedidos[[#This Row],[estado_operativo]]="ENTREGADO",tblPedidos[[#This Row],[ganancia_calc]],tblPedidos[[#This Row],[estado_operativo]]="DEVOLUCION",tblPedidos[[#This Row],[costo_devolucion_estimado]]),0)} -> 0 | V43: 0 | W43: 84900 | X43: 19020.5 | Y43: 50000 | Z43: 46043 | AA43: 1 | AB43: 0.91458333 | AC43: PENDIENTE | AD43: PENDIENTE | AE43: PENDIENTE
C44: 1060 | D44: 63452208 | E44: 46043 | F44: Gabriela Vázquez | G44: INTERRAPIDISIMO | J44: PENDIENTE | L44: CUNDINAMARCA | M44: BOGOTA | N44: Carrera 1A #12b-12 | O44: 3017227575 | P44: {=IFERROR(_xlfn.XLOOKUP(tblPedidos[[#This Row],[id_dropi]],tblNotas[[#This Row],[id__dropi]],tblNotas[[#This Row],[Notas Manuales]], “”, 0),"")} | R44: Quemador de grasa Lemme Burn 60 cáps x1 | S44: 17004.5 | T44: -17895.5 | U44: {=IFERROR(_xlfn.IFS(tblPedidos[[#This Row],[estado_operativo]]="ENTREGADO",tblPedidos[[#This Row],[ganancia_calc]],tblPedidos[[#This Row],[estado_operativo]]="DEVOLUCION",tblPedidos[[#This Row],[costo_devolucion_estimado]]),0)} -> 0 | V44: 0 | W44: 59900 | X44: 17895.5 | Y44: 25000 | Z44: 46043 | AA44: 1 | AB44: 0.91388889 | AC44: PENDIENTE | AD44: PENDIENTE | AE44: PENDIENTE
C45: 1057 | D45: 63451980 | E45: 46043 | F45: Luz marina Hernández | G45: INTERRAPIDISIMO | J45: PENDIENTE | L45: RISARALDA | M45: GUATICA | N45: Cliente recoge pedido en oficina de Interrapidisimo en Guatica cliente recoge en esa oficina | O45: 3145090463 | P45: {=IFERROR(_xlfn.XLOOKUP(tblPedidos[[#This Row],[id_dropi]],tblNotas[[#This Row],[id__dropi]],tblNotas[[#This Row],[Notas Manuales]], “”, 0),"")} | Q45: PEDIDO PARA RECOGER EN OFICINA DE INTERRAPIDISIMO | R45: DUO capilar ADIOS FRIZZ - 500ml x1 | S45: 32654.5 | T45: -13795.5 | U45: {=IFERROR(_xlfn.IFS(tblPedidos[[#This Row],[estado_operativo]]="ENTREGADO",tblPedidos[[#This Row],[ganancia_calc]],tblPedidos[[#This Row],[estado_operativo]]="DEVOLUCION",tblPedidos[[#This Row],[costo_devolucion_estimado]]),0)} -> 0 | V45: 0 | W45: 69900 | X45: 13795.5 | Y45: 23450 | Z45: 46043 | AA45: 1 | AB45: 0.9125 | AC45: PENDIENTE | AD45: PENDIENTE | AE45: PENDIENTE
C46: 1054 | D46: 63451880 | E46: 46043 | F46: Deicy jhojana meza | G46: INTERRAPIDISIMO | J46: PENDIENTE | L46: ARAUCA | M46: SARAVENA | N46: Calle 29 #3-55 Las flores | O46: 3157242805 | P46: {=IFERROR(_xlfn.XLOOKUP(tblPedidos[[#This Row],[id_dropi]],tblNotas[[#This Row],[id__dropi]],tblNotas[[#This Row],[Notas Manuales]], “”, 0),"")} | R46: DUO capilar ADIOS FRIZZ - 300 ml x1 | S46: 22054.5 | T46: -17895.5 | U46: {=IFERROR(_xlfn.IFS(tblPedidos[[#This Row],[estado_operativo]]="ENTREGADO",tblPedidos[[#This Row],[ganancia_calc]],tblPedidos[[#This Row],[estado_operativo]]="DEVOLUCION",tblPedidos[[#This Row],[costo_devolucion_estimado]]),0)} -> 0 | V46: 0 | W46: 59900 | X46: 17895.5 | Y46: 19950 | Z46: 46043 | AA46: 1 | AB46: 0.91180556 | AC46: PENDIENTE | AD46: PENDIENTE | AE46: PENDIENTE
C47: 1055 | D47: 63451840 | E47: 46043 | F47: Nery edith Motta | G47: INTERRAPIDISIMO | J47: PENDIENTE | L47: CAQUETA | M47: FLORENCIA | N47: Calle 24 #1C - 35 Barrio las Américas | O47: 3114454735 | P47: {=IFERROR(_xlfn.XLOOKUP(tblPedidos[[#This Row],[id_dropi]],tblNotas[[#This Row],[id__dropi]],tblNotas[[#This Row],[Notas Manuales]], “”, 0),"")} | Q47: Barrio las Américas | R47: Bee Venom BSWELL x1 + Beevana crema +Varicose veins x1 | S47: 17004.5 | T47: -17895.5 | U47: {=IFERROR(_xlfn.IFS(tblPedidos[[#This Row],[estado_operativo]]="ENTREGADO",tblPedidos[[#This Row],[ganancia_calc]],tblPedidos[[#This Row],[estado_operativo]]="DEVOLUCION",tblPedidos[[#This Row],[costo_devolucion_estimado]]),0)} -> 0 | V47: 0 | W47: 59900 | X47: 17895.5 | Y47: 25000 | Z47: 46043 | AA47: 1 | AB47: 0.91111111 | AC47: PENDIENTE | AD47: PENDIENTE | AE47: PENDIENTE
C48: 1056 | D48: 63451568 | E48: 46043 | F48: Rosa Barragan Barragan | G48: INTERRAPIDISIMO | J48: PENDIENTE | L48: NORTE DE SANTANDER | M48: CUCUTA | N48: Avenida 5ce #1an-07 El Tuna | O48: 3122426573 | P48: {=IFERROR(_xlfn.XLOOKUP(tblPedidos[[#This Row],[id_dropi]],tblNotas[[#This Row],[id__dropi]],tblNotas[[#This Row],[Notas Manuales]], “”, 0),"")} | R48: Quemador de grasa Lemme Burn 60 cáps x2 | S48: 20654.5 | T48: -19245.5 | U48: {=IFERROR(_xlfn.IFS(tblPedidos[[#This Row],[estado_operativo]]="ENTREGADO",tblPedidos[[#This Row],[ganancia_calc]],tblPedidos[[#This Row],[estado_operativo]]="DEVOLUCION",tblPedidos[[#This Row],[costo_devolucion_estimado]]),0)} -> 0 | V48: 0 | W48: 89900 | X48: 19245.5 | Y48: 50000 | Z48: 46043 | AA48: 1 | AB48: 0.90972222 | AC48: PENDIENTE | AD48: PENDIENTE | AE48: PENDIENTE
C49: 1046 | D49: 63451392 | E49: 46043 | F49: Gerardo lopez | G49: INTERRAPIDISIMO | J49: PENDIENTE | L49: CUNDINAMARCA | M49: FUSAGASUGA | N49: Cliente recoge pedido en oficina de Interrapidisimo en Fusagasuga / CENTRO cliente recoge en esa oficina | O49: 3113684684 | P49: {=IFERROR(_xlfn.XLOOKUP(tblPedidos[[#This Row],[id_dropi]],tblNotas[[#This Row],[id__dropi]],tblNotas[[#This Row],[Notas Manuales]], “”, 0),"")} | Q49: PEDIDO PARA RECOGER EN OFICINA DE INTERRAPIDISIMO | R49: Varicose veins crema para varices x2 + Bee Venom BSWELL x1 | S49: 17554.5 | T49: -13345.5 | U49: {=IFERROR(_xlfn.IFS(tblPedidos[[#This Row],[estado_operativo]]="ENTREGADO",tblPedidos[[#This Row],[ganancia_calc]],tblPedidos[[#This Row],[estado_operativo]]="DEVOLUCION",tblPedidos[[#This Row],[costo_devolucion_estimado]]),0)} -> 0 | V49: 0 | W49: 59900 | X49: 13345.5 | Y49: 29000 | Z49: 46043 | AA49: 1 | AB49: 0.90833333 | AC49: PENDIENTE | AD49: PENDIENTE | AE49: PENDIENTE
C50: 1036 | D50: 63450586 | E50: 46043 | F50: Rosalba Caballero | G50: JAMV-DRIVE | J50: PENDIENTE | L50: CUNDINAMARCA | M50: BOGOTA | N50: Carrera 56 #152b-71, Barrio Mazuren, Localidad Suba, Picabia | O50: 3123252046 | P50: {=IFERROR(_xlfn.XLOOKUP(tblPedidos[[#This Row],[id_dropi]],tblNotas[[#This Row],[id__dropi]],tblNotas[[#This Row],[Notas Manuales]], “”, 0),"")} | R50: Bee Venom BSWELL x1 + Beevana crema +Varicose veins x1 | S50: 22103 | T50: -10237.6 | U50: {=IFERROR(_xlfn.IFS(tblPedidos[[#This Row],[estado_operativo]]="ENTREGADO",tblPedidos[[#This Row],[ganancia_calc]],tblPedidos[[#This Row],[estado_operativo]]="DEVOLUCION",tblPedidos[[#This Row],[costo_devolucion_estimado]]),0)} -> 0 | V50: 0 | W50: 59900 | X50: 12797 | Y50: 25000 | Z50: 46043 | AA50: 1 | AB50: 0.90208333 | AC50: PENDIENTE | AD50: PENDIENTE | AE50: PENDIENTE
C51: 1037 | D51: 63449647 | E51: 46043 | F51: Jeniree Pernia | G51: ENVIA | J51: PENDIENTE | L51: MAGDALENA | M51: SANTA MARTA | N51: Calle 124 #8-24 de tras de caucho van, Barrio vista hermosa | O51: 3008669416 | P51: {=IFERROR(_xlfn.XLOOKUP(tblPedidos[[#This Row],[id_dropi]],tblNotas[[#This Row],[id__dropi]],tblNotas[[#This Row],[Notas Manuales]], “”, 0),"")} | R51: Quemador de grasa Lemme Burn 60 cáps x2 | S51: 23336.5 | T51: -13250.8 | U51: {=IFERROR(_xlfn.IFS(tblPedidos[[#This Row],[estado_operativo]]="ENTREGADO",tblPedidos[[#This Row],[ganancia_calc]],tblPedidos[[#This Row],[estado_operativo]]="DEVOLUCION",tblPedidos[[#This Row],[costo_devolucion_estimado]]),0)} -> 0 | V51: 0 | W51: 89900 | X51: 16563.5 | Y51: 50000 | Z51: 46043 | AA51: 1 | AB51: 0.89513889 | AC51: PENDIENTE | AD51: PENDIENTE | AE51: PENDIENTE
C52: 1038 | D52: 63449276 | E52: 46043 | F52: Leidy Yumara Rodríguez Buitrago | G52: INTERRAPIDISIMO | J52: PENDIENTE | L52: HUILA | M52: NEIVA | N52: Calle 14 #20-05 apto 103 primero de mayo | O52: 3208245763 | P52: {=IFERROR(_xlfn.XLOOKUP(tblPedidos[[#This Row],[id_dropi]],tblNotas[[#This Row],[id__dropi]],tblNotas[[#This Row],[Notas Manuales]], “”, 0),"")} | R52: Quemador de grasa Lemme Burn 60 cáps x2 | S52: 20654.5 | T52: -19245.5 | U52: {=IFERROR(_xlfn.IFS(tblPedidos[[#This Row],[estado_operativo]]="ENTREGADO",tblPedidos[[#This Row],[ganancia_calc]],tblPedidos[[#This Row],[estado_operativo]]="DEVOLUCION",tblPedidos[[#This Row],[costo_devolucion_estimado]]),0)} -> 0 | V52: 0 | W52: 89900 | X52: 19245.5 | Y52: 50000 | Z52: 46043 | AA52: 1 | AB52: 0.89236111 | AC52: PENDIENTE | AD52: PENDIENTE | AE52: PENDIENTE
C53: 1035 | D53: 63448980 | E53: 46043 | F53: Yovanny Gómez | G53: INTERRAPIDISIMO | J53: PENDIENTE | L53: NARIÑO | M53: LA LLANADA | N53: Calle 2 -32 barrio corazón de Jesús | O53: 3183177323 | P53: {=IFERROR(_xlfn.XLOOKUP(tblPedidos[[#This Row],[id_dropi]],tblNotas[[#This Row],[id__dropi]],tblNotas[[#This Row],[Notas Manuales]], “”, 0),"")} | R53: Ampolleta Brillo y Suavidad x10ml x2 + DUO capilar ADIOS FRIZZ - 300 ml x1 | S53: 34494.5 | T53: -19155.5 | U53: {=IFERROR(_xlfn.IFS(tblPedidos[[#This Row],[estado_operativo]]="ENTREGADO",tblPedidos[[#This Row],[ganancia_calc]],tblPedidos[[#This Row],[estado_operativo]]="DEVOLUCION",tblPedidos[[#This Row],[costo_devolucion_estimado]]),0)} -> 0 | V53: 0 | W53: 87900 | X53: 19155.5 | Y53: 34250 | Z53: 46043 | AA53: 1 | AB53: 0.88958333 | AC53: PENDIENTE | AD53: PENDIENTE | AE53: PENDIENTE
C54: 1032 | D54: 63448641 | E54: 46043 | F54: Felipe Nogary | G54: INTERRAPIDISIMO | J54: PENDIENTE | L54: RISARALDA | M54: APIA | N54: Cliente recoge pedido en oficina de Interrapidisimo en Apia cliente recoge en esa oficina | O54: 3106270678 | P54: {=IFERROR(_xlfn.XLOOKUP(tblPedidos[[#This Row],[id_dropi]],tblNotas[[#This Row],[id__dropi]],tblNotas[[#This Row],[Notas Manuales]], “”, 0),"")} | Q54: PEDIDO PARA RECOGER EN OFICINA DE INTERRAPIDISIMO | R54: Aceite de Batana x2 | S54: 26779.5 | T54: -18120.5 | U54: {=IFERROR(_xlfn.IFS(tblPedidos[[#This Row],[estado_operativo]]="ENTREGADO",tblPedidos[[#This Row],[ganancia_calc]],tblPedidos[[#This Row],[estado_operativo]]="DEVOLUCION",tblPedidos[[#This Row],[costo_devolucion_estimado]]),0)} -> 0 | V54: 0 | W54: 64900 | X54: 18120.5 | Y54: 20000 | Z54: 46043 | AA54: 1 | AB54: 0.8875 | AC54: PENDIENTE | AD54: PENDIENTE | AE54: PENDIENTE
C55: 1033 | D55: 63448398 | E55: 46043 | F55: Diana Patricia Garzon | G55: INTERRAPIDISIMO | J55: PENDIENTE | L55: RISARALDA | M55: BELEN DE UMBRIA | N55: Calle 3 # 11 - 17 | O55: 3127407674 | P55: {=IFERROR(_xlfn.XLOOKUP(tblPedidos[[#This Row],[id_dropi]],tblNotas[[#This Row],[id__dropi]],tblNotas[[#This Row],[Notas Manuales]], “”, 0),"")} | R55: Cepillo Plancha Secador 2 en 1 Alisador x1 | S55: 22829.5 | T55: -17670.5 | U55: {=IFERROR(_xlfn.IFS(tblPedidos[[#This Row],[estado_operativo]]="ENTREGADO",tblPedidos[[#This Row],[ganancia_calc]],tblPedidos[[#This Row],[estado_operativo]]="DEVOLUCION",tblPedidos[[#This Row],[costo_devolucion_estimado]]),0)} -> 0 | V55: 0 | W55: 54900 | X55: 17670.5 | Y55: 14400 | Z55: 46043 | AA55: 1 | AB55: 0.88611111 | AC55: PENDIENTE | AD55: PENDIENTE | AE55: PENDIENTE
C56: 1034 | D56: 63448084 | E56: 46043 | F56: Ana Sofia Amaya Castañeda | G56: INTERRAPIDISIMO | J56: PENDIENTE | L56: CUNDINAMARCA | M56: EL COLEGIO (MESITAS) | N56: Calle 8 # 8A-26, El Colegio, Mesitas del Colegio | O56: 3208632837 | P56: {=IFERROR(_xlfn.XLOOKUP(tblPedidos[[#This Row],[id_dropi]],tblNotas[[#This Row],[id__dropi]],tblNotas[[#This Row],[Notas Manuales]], “”, 0),"")} | R56: Quemador de grasa Lemme Burn 60 cáps x2 | S56: 15879.5 | T56: -19020.5 | U56: {=IFERROR(_xlfn.IFS(tblPedidos[[#This Row],[estado_operativo]]="ENTREGADO",tblPedidos[[#This Row],[ganancia_calc]],tblPedidos[[#This Row],[estado_operativo]]="DEVOLUCION",tblPedidos[[#This Row],[costo_devolucion_estimado]]),0)} -> 0 | V56: 0 | W56: 84900 | X56: 19020.5 | Y56: 50000 | Z56: 46043 | AA56: 1 | AB56: 0.88333333 | AC56: PENDIENTE | AD56: PENDIENTE | AE56: PENDIENTE
C57: 1043 | D57: 63447983 | E57: 46043 | F57: Dora Urrego Vargas | G57: INTERRAPIDISIMO | J57: PENDIENTE | L57: ANTIOQUIA | M57: URRAO | N57: Cliente recoge pedido en oficina de Interrapidisimo en Urrao cliente recoge en esa oficina | O57: 3052070026 | P57: {=IFERROR(_xlfn.XLOOKUP(tblPedidos[[#This Row],[id_dropi]],tblNotas[[#This Row],[id__dropi]],tblNotas[[#This Row],[Notas Manuales]], “”, 0),"")} | Q57: PEDIDO PARA RECOGER EN OFICINA DE INTERRAPIDISIMO | R57: Quemador de grasa Lemme Burn 60 cáps x2 | S57: 20654.5 | T57: -19245.5 | U57: {=IFERROR(_xlfn.IFS(tblPedidos[[#This Row],[estado_operativo]]="ENTREGADO",tblPedidos[[#This Row],[ganancia_calc]],tblPedidos[[#This Row],[estado_operativo]]="DEVOLUCION",tblPedidos[[#This Row],[costo_devolucion_estimado]]),0)} -> 0 | V57: 0 | W57: 89900 | X57: 19245.5 | Y57: 50000 | Z57: 46043 | AA57: 1 | AB57: 0.88194444 | AC57: PENDIENTE | AD57: PENDIENTE | AE57: PENDIENTE
C58: 1044 | D58: 63447946 | E58: 46043 | F58: Elisa Cuervo | G58: INTERRAPIDISIMO | J58: PENDIENTE | L58: CUNDINAMARCA | M58: BOGOTA | N58: Calle 18 #104b-50, Fontibón | O58: 3114472950 | P58: {=IFERROR(_xlfn.XLOOKUP(tblPedidos[[#This Row],[id_dropi]],tblNotas[[#This Row],[id__dropi]],tblNotas[[#This Row],[Notas Manuales]], “”, 0),"")} | R58: Quemador de grasa Lemme Burn 60 cáps x2 | S58: 20654.5 | T58: -19245.5 | U58: {=IFERROR(_xlfn.IFS(tblPedidos[[#This Row],[estado_operativo]]="ENTREGADO",tblPedidos[[#This Row],[ganancia_calc]],tblPedidos[[#This Row],[estado_operativo]]="DEVOLUCION",tblPedidos[[#This Row],[costo_devolucion_estimado]]),0)} -> 0 | V58: 0 | W58: 89900 | X58: 19245.5 | Y58: 50000 | Z58: 46043 | AA58: 1 | AB58: 0.88194444 | AC58: PENDIENTE | AD58: PENDIENTE | AE58: PENDIENTE
C59: 1045 | D59: 63447920 | E59: 46043 | F59: Digneris Vides Muñoz | G59: INTERRAPIDISIMO | J59: PENDIENTE | L59: CESAR | M59: PELAYA | N59: Cliente recoge pedido en oficina de Interrapidisimo en Pelaya cliente recoge en esa oficina | O59: 3215511581 | P59: {=IFERROR(_xlfn.XLOOKUP(tblPedidos[[#This Row],[id_dropi]],tblNotas[[#This Row],[id__dropi]],tblNotas[[#This Row],[Notas Manuales]], “”, 0),"")} | Q59: PEDIDO PARA RECOGER EN OFICINA DE INTERRAPIDISIMO | R59: DUO capilar ADIOS FRIZZ - 300 ml x1 | S59: 22054.5 | T59: -17895.5 | U59: {=IFERROR(_xlfn.IFS(tblPedidos[[#This Row],[estado_operativo]]="ENTREGADO",tblPedidos[[#This Row],[ganancia_calc]],tblPedidos[[#This Row],[estado_operativo]]="DEVOLUCION",tblPedidos[[#This Row],[costo_devolucion_estimado]]),0)} -> 0 | V59: 0 | W59: 59900 | X59: 17895.5 | Y59: 19950 | Z59: 46043 | AA59: 1 | AB59: 0.88125 | AC59: PENDIENTE | AD59: PENDIENTE | AE59: PENDIENTE
C60: 1042 | D60: 63447795 | E60: 46043 | F60: Jeniffer Apónte | G60: INTERRAPIDISIMO | J60: PENDIENTE | L60: CUNDINAMARCA | M60: BOGOTA | N60: Calle 50 sur #37-27, ENTREGAR DESPUES DE LAS 4 | O60: 3166186409 | P60: {=IFERROR(_xlfn.XLOOKUP(tblPedidos[[#This Row],[id_dropi]],tblNotas[[#This Row],[id__dropi]],tblNotas[[#This Row],[Notas Manuales]], “”, 0),"")} | R60: DUO capilar ADIOS FRIZZ - 500ml x1 | S60: 28104.5 | T60: -18345.5 | U60: {=IFERROR(_xlfn.IFS(tblPedidos[[#This Row],[estado_operativo]]="ENTREGADO",tblPedidos[[#This Row],[ganancia_calc]],tblPedidos[[#This Row],[estado_operativo]]="DEVOLUCION",tblPedidos[[#This Row],[costo_devolucion_estimado]]),0)} -> 0 | V60: 0 | W60: 69900 | X60: 18345.5 | Y60: 23450 | Z60: 46043 | AA60: 1 | AB60: 0.88055556 | AC60: PENDIENTE | AD60: PENDIENTE | AE60: PENDIENTE
C61: 1039 | D61: 63447459 | E61: 46043 | F61: Paola Arenas | G61: ENVIA | J61: PENDIENTE | L61: ANTIOQUIA | M61: MEDELLIN | N61: Carrera 92e #83-22 Robledo villa Sofía | O61: 3217771837 | P61: {=IFERROR(_xlfn.XLOOKUP(tblPedidos[[#This Row],[id_dropi]],tblNotas[[#This Row],[id__dropi]],tblNotas[[#This Row],[Notas Manuales]], “”, 0),"")} | R61: DUO capilar ADIOS FRIZZ - 300 ml x1 | S61: 26896.5 | T61: -10442.8 | U61: {=IFERROR(_xlfn.IFS(tblPedidos[[#This Row],[estado_operativo]]="ENTREGADO",tblPedidos[[#This Row],[ganancia_calc]],tblPedidos[[#This Row],[estado_operativo]]="DEVOLUCION",tblPedidos[[#This Row],[costo_devolucion_estimado]]),0)} -> 0 | V61: 0 | W61: 59900 | X61: 13053.5 | Y61: 19950 | Z61: 46043 | AA61: 1 | AB61: 0.87847222 | AC61: PENDIENTE | AD61: PENDIENTE | AE61: PENDIENTE
C62: 1040 | D62: 63437459 | E62: 46043 | F62: Fanny Yanira Tamayo Tellez | G62: ENVIA | J62: PENDIENTE | L62: CUNDINAMARCA | M62: BOGOTA | N62: Carrera 18b bis #91b-24sur, Mochuelo bajó-ciudad bolivar | O62: 3235141385 | P62: {=IFERROR(_xlfn.XLOOKUP(tblPedidos[[#This Row],[id_dropi]],tblNotas[[#This Row],[id__dropi]],tblNotas[[#This Row],[Notas Manuales]], “”, 0),"")} | R62: DUO capilar ADIOS FRIZZ - 500ml x1 | S62: 30786.5 | T62: -12530.8 | U62: {=IFERROR(_xlfn.IFS(tblPedidos[[#This Row],[estado_operativo]]="ENTREGADO",tblPedidos[[#This Row],[ganancia_calc]],tblPedidos[[#This Row],[estado_operativo]]="DEVOLUCION",tblPedidos[[#This Row],[costo_devolucion_estimado]]),0)} -> 0 | V62: 0 | W62: 69900 | X62: 15663.5 | Y62: 23450 | Z62: 46043 | AA62: 1 | AB62: 0.79236111 | AC62: PENDIENTE | AD62: PENDIENTE | AE62: PENDIENTE
C63: 1041 | D63: 63437291 | E63: 46043 | F63: Olga Rocío Guzmán | G63: JAMV-DRIVE | J63: PENDIENTE | L63: CUNDINAMARCA | M63: BOGOTA | N63: Diagonal 19 #95i-15. PRACO DIDACOL, fontibon | O63: 3219682408 | P63: {=IFERROR(_xlfn.XLOOKUP(tblPedidos[[#This Row],[id_dropi]],tblNotas[[#This Row],[id__dropi]],tblNotas[[#This Row],[Notas Manuales]], “”, 0),"")} | R63: Quemador de grasa Lemme Burn 60 cáps x2 | S63: 21203 | T63: -14957.6 | U63: {=IFERROR(_xlfn.IFS(tblPedidos[[#This Row],[estado_operativo]]="ENTREGADO",tblPedidos[[#This Row],[ganancia_calc]],tblPedidos[[#This Row],[estado_operativo]]="DEVOLUCION",tblPedidos[[#This Row],[costo_devolucion_estimado]]),0)} -> 0 | V63: 0 | W63: 89900 | X63: 18697 | Y63: 50000 | Z63: 46043 | AA63: 1 | AB63: 0.79097222 | AC63: PENDIENTE | AD63: PENDIENTE | AE63: PENDIENTE
C64: 966 | D64: 63347170 | E64: 46042 | F64: Astrid pirazan | G64: INTERRAPIDISIMO | J64: ORIGEN | K64: 240044550582 | L64: CUNDINAMARCA | M64: CHIA | N64: Calle 10 #1E-02 | O64: 3206407099 | P64: {=IFERROR(_xlfn.XLOOKUP(tblPedidos[[#This Row],[id_dropi]],tblNotas[[#This Row],[id__dropi]],tblNotas[[#This Row],[Notas Manuales]], “”, 0),"")} | R64: Aceite de Batana x2 + Aceite de Batana x2 | S64: 32729.5 | T64: -12170.5 | U64: {=IFERROR(_xlfn.IFS(tblPedidos[[#This Row],[estado_operativo]]="ENTREGADO",tblPedidos[[#This Row],[ganancia_calc]],tblPedidos[[#This Row],[estado_operativo]]="DEVOLUCION",tblPedidos[[#This Row],[costo_devolucion_estimado]]),0)} -> 0 | V64: 0 | W64: 64900 | X64: 12170.5 | Y64: 20000 | Z64: 46043 | AA64: 1 | AB64: 0.45833333 | AC64: PREPARADO PARA TRANSPORTADORA | AD64: PREPARADO PARA TRANSPORTADORA | AE64: ORIGEN
C65: 967 | D65: 63347064 | E65: 46042 | F65: Edilma García | G65: ENVIA | J65: ORIGEN | K65: 024032305856 | L65: ANTIOQUIA | M65: BELLO | N65: Carrera 62C # 69B-54 Barrio Bellavista urbanización Goretti. Punto De Referencia Cancha Sintética Goretty. | O65: 3117428648 | P65: {=IFERROR(_xlfn.XLOOKUP(tblPedidos[[#This Row],[id_dropi]],tblNotas[[#This Row],[id__dropi]],tblNotas[[#This Row],[Notas Manuales]], “”, 0),"")} | R65: Quemador de grasa Lemme Burn 60 cáps x2 + Quemador de grasa Lemme Burn 60 cáps x2 | S65: 23336.5 | T65: -13250.8 | U65: {=IFERROR(_xlfn.IFS(tblPedidos[[#This Row],[estado_operativo]]="ENTREGADO",tblPedidos[[#This Row],[ganancia_calc]],tblPedidos[[#This Row],[estado_operativo]]="DEVOLUCION",tblPedidos[[#This Row],[costo_devolucion_estimado]]),0)} -> 0 | V65: 0 | W65: 89900 | X65: 16563.5 | Y65: 50000 | Z65: 46043 | AA65: 1 | AB65: 0.91111111 | AC65: EN BODEGA ORIGEN | AD65: EN BODEGA ORIGEN | AE65: ORIGEN
C66: 968 | D66: 63347018 | E66: 46042 | F66: Tatiana Madrid Sánchez | G66: ENVIA | J66: ORIGEN | K66: 024032305857 | L66: ANTIOQUIA | M66: MEDELLIN | N66: Carrera 47 #50-24 oficina 903- edificio furatena | O66: 3137368197 | P66: {=IFERROR(_xlfn.XLOOKUP(tblPedidos[[#This Row],[id_dropi]],tblNotas[[#This Row],[id__dropi]],tblNotas[[#This Row],[Notas Manuales]], “”, 0),"")} | R66: Quemador de grasa Lemme Burn 60 cáps x1 + Quemador de grasa Lemme Burn 60 cáps x1 | S66: 19686.5 | T66: -12170.8 | U66: {=IFERROR(_xlfn.IFS(tblPedidos[[#This Row],[estado_operativo]]="ENTREGADO",tblPedidos[[#This Row],[ganancia_calc]],tblPedidos[[#This Row],[estado_operativo]]="DEVOLUCION",tblPedidos[[#This Row],[costo_devolucion_estimado]]),0)} -> 0 | V66: 0 | W66: 59900 | X66: 15213.5 | Y66: 25000 | Z66: 46043 | AA66: 1 | AB66: 0.91180556 | AC66: EN BODEGA ORIGEN | AD66: EN BODEGA ORIGEN | AE66: ORIGEN
C67: 963 | D67: 63336813 | E67: 46042 | F67: Mary Agudelo | G67: JAMV-DRIVE | J67: ORIGEN | K67: WCO2000463441 | L67: CUNDINAMARCA | M67: BOGOTA | N67: Calle 59 sur #23d- 81, Casa linda, ciudad bolivar | O67: 3118908158 | P67: {=IFERROR(_xlfn.XLOOKUP(tblPedidos[[#This Row],[id_dropi]],tblNotas[[#This Row],[id__dropi]],tblNotas[[#This Row],[Notas Manuales]], “”, 0),"")} | R67: Varicose veins crema para varices x1 + Bee Venom BSWELL x1 + Beevana crema dolores - 1 x1 + Varicose veins crema para varices x1 + Bee Venom BSWELL x1 + Beevana crema dolores - 1 x1 | S67: 21103 | T67: -10237.6 | U67: {=IFERROR(_xlfn.IFS(tblPedidos[[#This Row],[estado_operativo]]="ENTREGADO",tblPedidos[[#This Row],[ganancia_calc]],tblPedidos[[#This Row],[estado_operativo]]="DEVOLUCION",tblPedidos[[#This Row],[costo_devolucion_estimado]]),0)} -> 0 | V67: 0 | W67: 59900 | X67: 12797 | Y67: 26000 | Z67: 46043 | AA67: 1 | AB67: 0.77083333 | AC67: EN BODEGA ORIGEN | AD67: EN BODEGA ORIGEN | AE67: ORIGEN
C68: 964 | D68: 63336724 | E68: 46042 | F68: Monica penagos | G68: INTERRAPIDISIMO | J68: ORIGEN | K68: 240044572572 | L68: CUNDINAMARCA | M68: BOGOTA | N68: Calle 2b-56a-29 Studio lash | O68: 3054609841 | P68: {=IFERROR(_xlfn.XLOOKUP(tblPedidos[[#This Row],[id_dropi]],tblNotas[[#This Row],[id__dropi]],tblNotas[[#This Row],[Notas Manuales]], “”, 0),"")} | R68: Quemador de grasa Lemme Burn 60 cáps x1 + Quemador de grasa Lemme Burn 60 cáps x1 | S68: 17004.5 | T68: -17895.5 | U68: {=IFERROR(_xlfn.IFS(tblPedidos[[#This Row],[estado_operativo]]="ENTREGADO",tblPedidos[[#This Row],[ganancia_calc]],tblPedidos[[#This Row],[estado_operativo]]="DEVOLUCION",tblPedidos[[#This Row],[costo_devolucion_estimado]]),0)} -> 0 | V68: 0 | W68: 59900 | X68: 17895.5 | Y68: 25000 | Z68: 46043 | AA68: 1 | AB68: 0.83958333 | AC68: ADMITIDA | AD68: ADMITIDA | AE68: ORIGEN
C69: 965 | D69: 63336597 | E69: 46042 | F69: Graciela Naranjo Suárez | G69: INTERRAPIDISIMO | J69: ORIGEN | K69: 240044552711 | L69: CUNDINAMARCA | M69: BOGOTA | N69: Calle 1f #19C-14, Eduardo Santos | O69: 3023278652 | P69: {=IFERROR(_xlfn.XLOOKUP(tblPedidos[[#This Row],[id_dropi]],tblNotas[[#This Row],[id__dropi]],tblNotas[[#This Row],[Notas Manuales]], “”, 0),"")} | R69: Cepillo Plancha Secador 2 en 1 Alisador x1 + Cepillo Plancha Secador 2 en 1 Alisador x1 | S69: 28779.5 | T69: -11720.5 | U69: {=IFERROR(_xlfn.IFS(tblPedidos[[#This Row],[estado_operativo]]="ENTREGADO",tblPedidos[[#This Row],[ganancia_calc]],tblPedidos[[#This Row],[estado_operativo]]="DEVOLUCION",tblPedidos[[#This Row],[costo_devolucion_estimado]]),0)} -> 0 | V69: 0 | W69: 54900 | X69: 11720.5 | Y69: 14400 | Z69: 46043 | AA69: 1 | AB69: 0.70347222 | AC69: PREPARADO PARA TRANSPORTADORA | AD69: PREPARADO PARA TRANSPORTADORA | AE69: ORIGEN
C70: 969 | D70: 63336480 | E70: 46042 | F70: Rosa Elvira Angarita Saez | G70: INTERRAPIDISIMO | J70: ORIGEN | K70: 240044553354 | L70: META | M70: EL CASTILLO | N70: Cliente recoge pedido en oficina de Interrapidisimo en El Castillo cliente recoge en esa oficina | O70: 3125155433 | P70: {=IFERROR(_xlfn.XLOOKUP(tblPedidos[[#This Row],[id_dropi]],tblNotas[[#This Row],[id__dropi]],tblNotas[[#This Row],[Notas Manuales]], “”, 0),"")} | Q70: PEDIDO PARA RECOGER EN OFICINA DE INTERRAPIDISIMO | R70: Varicose veins crema para varices x1 + Bee Venom BSWELL x1 + Beevana crema dolores - 1 x1 + Varicose veins crema para varices x1 + Bee Venom BSWELL x1 + Beevana crema dolores - 1 x1 | S70: 16004.5 | T70: -17895.5 | U70: {=IFERROR(_xlfn.IFS(tblPedidos[[#This Row],[estado_operativo]]="ENTREGADO",tblPedidos[[#This Row],[ganancia_calc]],tblPedidos[[#This Row],[estado_operativo]]="DEVOLUCION",tblPedidos[[#This Row],[costo_devolucion_estimado]]),0)} -> 0 | V70: 0 | W70: 59900 | X70: 17895.5 | Y70: 26000 | Z70: 46043 | AA70: 1 | AB70: 0.75486111 | AC70: ADMITIDA | AD70: ADMITIDA | AE70: ORIGEN
C71: 973 | D71: 63336206 | E71: 46042 | F71: enederlanda fiscal Gutiérrez | G71: INTERRAPIDISIMO | J71: ORIGEN | K71: 240044553434 | L71: META | M71: SAN CARLOS DE GUAROA | N71: Cliente recoge pedido en oficina de Interrapidisimo en San Carlos De Guaroa cliente recoge en esa oficina | O71: 3207870294 | P71: {=IFERROR(_xlfn.XLOOKUP(tblPedidos[[#This Row],[id_dropi]],tblNotas[[#This Row],[id__dropi]],tblNotas[[#This Row],[Notas Manuales]], “”, 0),"")} | Q71: PEDIDO PARA RECOGER EN OFICINA DE INTERRAPIDISIMO | R71: Varicose veins crema para varices x1 + Bee Venom BSWELL x1 + Beevana crema dolores - 1 x1 + Varicose veins crema para varices x1 + Bee Venom BSWELL x1 + Beevana crema dolores - 1 x1 | S71: 16004.5 | T71: -17895.5 | U71: {=IFERROR(_xlfn.IFS(tblPedidos[[#This Row],[estado_operativo]]="ENTREGADO",tblPedidos[[#This Row],[ganancia_calc]],tblPedidos[[#This Row],[estado_operativo]]="DEVOLUCION",tblPedidos[[#This Row],[costo_devolucion_estimado]]),0)} -> 0 | V71: 0 | W71: 59900 | X71: 17895.5 | Y71: 26000 | Z71: 46043 | AA71: 1 | AB71: 0.75486111 | AC71: ADMITIDA | AD71: ADMITIDA | AE71: ORIGEN
C72: 974 | D72: 63336096 | E72: 46042 | F72: Beatriz Elena Arango Martínez | G72: ENVIA | J72: ORIGEN | K72: 014155840200 | L72: ANTIOQUIA | M72: MEDELLIN | N72: Carrera 39 #84-39, interor132 | O72: 3178073990 | P72: {=IFERROR(_xlfn.XLOOKUP(tblPedidos[[#This Row],[id_dropi]],tblNotas[[#This Row],[id__dropi]],tblNotas[[#This Row],[Notas Manuales]], “”, 0),"")} | R72: Varicose veins crema para varices x1 + Bee Venom BSWELL x1 + Beevana crema dolores - 1 x1 + Varicose veins crema para varices x1 + Bee Venom BSWELL x1 + Beevana crema dolores - 1 x1 | S72: 18686.5 | T72: -12170.8 | U72: {=IFERROR(_xlfn.IFS(tblPedidos[[#This Row],[estado_operativo]]="ENTREGADO",tblPedidos[[#This Row],[ganancia_calc]],tblPedidos[[#This Row],[estado_operativo]]="DEVOLUCION",tblPedidos[[#This Row],[costo_devolucion_estimado]]),0)} -> 0 | V72: 0 | W72: 59900 | X72: 15213.5 | Y72: 26000 | Z72: 46043 | AA72: 1 | AB72: 0.73958333 | AC72: EN BODEGA ORIGEN | AD72: EN BODEGA ORIGEN | AE72: ORIGEN
C73: 975 | D73: 63335932 | E73: 46042 | F73: Henry Alfonso González | G73: INTERRAPIDISIMO | J73: ORIGEN | K73: 240044553477 | L73: CUNDINAMARCA | M73: SOACHA | N73: Carrera 13 #26-30s , barrio compartir | O73: 3239845595 | P73: {=IFERROR(_xlfn.XLOOKUP(tblPedidos[[#This Row],[id_dropi]],tblNotas[[#This Row],[id__dropi]],tblNotas[[#This Row],[Notas Manuales]], “”, 0),"")} | R73: Varicose veins crema para varices x1 + Bee Venom BSWELL x1 + Beevana crema dolores - 1 x1 + Varicose veins crema para varices x1 + Bee Venom BSWELL x1 + Beevana crema dolores - 1 x1 | S73: 21954.5 | T73: -11945.5 | U73: {=IFERROR(_xlfn.IFS(tblPedidos[[#This Row],[estado_operativo]]="ENTREGADO",tblPedidos[[#This Row],[ganancia_calc]],tblPedidos[[#This Row],[estado_operativo]]="DEVOLUCION",tblPedidos[[#This Row],[costo_devolucion_estimado]]),0)} -> 0 | V73: 0 | W73: 59900 | X73: 11945.5 | Y73: 26000 | Z73: 46043 | AA73: 1 | AB73: 0.75486111 | AC73: ADMITIDA | AD73: ADMITIDA | AE73: ORIGEN
C74: 970 | D74: 63335276 | E74: 46042 | F74: Maire Rey | G74: INTERRAPIDISIMO | J74: ORIGEN | K74: 240044572612 | L74: CUNDINAMARCA | M74: CAQUEZA | N74: Cliente recoge pedido en oficina de Interrapidisimo en Caqueza cliente recoge en esa oficina | O74: 3205645903 | P74: {=IFERROR(_xlfn.XLOOKUP(tblPedidos[[#This Row],[id_dropi]],tblNotas[[#This Row],[id__dropi]],tblNotas[[#This Row],[Notas Manuales]], “”, 0),"")} | Q74: PEDIDO PARA RECOGER EN OFICINA DE INTERRAPIDISIMO | R74: Quemador de grasa Lemme Burn 60 cáps x2 + Quemador de grasa Lemme Burn 60 cáps x2 | S74: 20654.5 | T74: -19245.5 | U74: {=IFERROR(_xlfn.IFS(tblPedidos[[#This Row],[estado_operativo]]="ENTREGADO",tblPedidos[[#This Row],[ganancia_calc]],tblPedidos[[#This Row],[estado_operativo]]="DEVOLUCION",tblPedidos[[#This Row],[costo_devolucion_estimado]]),0)} -> 0 | V74: 0 | W74: 89900 | X74: 19245.5 | Y74: 50000 | Z74: 46043 | AA74: 1 | AB74: 0.83958333 | AC74: ADMITIDA | AD74: ADMITIDA | AE74: ORIGEN
C75: 971 | D75: 63335216 | E75: 46042 | F75: Nuris Contreras | G75: INTERRAPIDISIMO | J75: ORIGEN | K75: 240044550330 | L75: SUCRE | M75: TOLU VIEJO | N75: Cliente recoge pedido en oficina INTERRAPIDISIMO Diagonal 3 #3A-55 calle San José | O75: 3113663080 | P75: {=IFERROR(_xlfn.XLOOKUP(tblPedidos[[#This Row],[id_dropi]],tblNotas[[#This Row],[id__dropi]],tblNotas[[#This Row],[Notas Manuales]], “”, 0),"")} | Q75: PEDIDO PARA RECOGER EN OFICINA DE INTERRAPIDISIMO | R75: Varicose veins crema para varices x1 + Bee Venom BSWELL x1 + Beevana crema dolores - 1 x1 + Varicose veins crema para varices x1 + Bee Venom BSWELL x1 + Beevana crema dolores - 1 x1 | S75: 16004.5 | T75: -17895.5 | U75: {=IFERROR(_xlfn.IFS(tblPedidos[[#This Row],[estado_operativo]]="ENTREGADO",tblPedidos[[#This Row],[ganancia_calc]],tblPedidos[[#This Row],[estado_operativo]]="DEVOLUCION",tblPedidos[[#This Row],[costo_devolucion_estimado]]),0)} -> 0 | V75: 0 | W75: 59900 | X75: 17895.5 | Y75: 26000 | Z75: 46043 | AA75: 1 | AB75: 0.75486111 | AC75: ADMITIDA | AD75: ADMITIDA | AE75: ORIGEN
C76: 972 | D76: 63335061 | E76: 46042 | F76: Edilberto Suárez | G76: INTERRAPIDISIMO | J76: ORIGEN | K76: 240044550346 | L76: BOYACA | M76: DUITAMA | N76: Calle 20 #26-26 tienda las joyas | O76: 3143333921 | P76: {=IFERROR(_xlfn.XLOOKUP(tblPedidos[[#This Row],[id_dropi]],tblNotas[[#This Row],[id__dropi]],tblNotas[[#This Row],[Notas Manuales]], “”, 0),"")} | R76: Varicose veins crema para varices x1 + Bee Venom BSWELL x1 + Beevana crema dolores - 1 x1 + Varicose veins crema para varices x1 + Bee Venom BSWELL x1 + Beevana crema dolores - 1 x1 | S76: 20554.5 | T76: -13345.5 | U76: {=IFERROR(_xlfn.IFS(tblPedidos[[#This Row],[estado_operativo]]="ENTREGADO",tblPedidos[[#This Row],[ganancia_calc]],tblPedidos[[#This Row],[estado_operativo]]="DEVOLUCION",tblPedidos[[#This Row],[costo_devolucion_estimado]]),0)} -> 0 | V76: 0 | W76: 59900 | X76: 13345.5 | Y76: 26000 | Z76: 46043 | AA76: 1 | AB76: 0.75486111 | AC76: ADMITIDA | AD76: ADMITIDA | AE76: ORIGEN
C77: 953 | D77: 63334868 | E77: 46042 | F77: Cindy pulgarín | G77: ENVIA | J77: ORIGEN | K77: 014155839833 | L77: ATLANTICO | M77: BARRANQUILLA | N77: Transversal 3B #26-222, CS 104, Barranquilla, Ciudad del Mar | O77: 3021274496 | P77: {=IFERROR(_xlfn.XLOOKUP(tblPedidos[[#This Row],[id_dropi]],tblNotas[[#This Row],[id__dropi]],tblNotas[[#This Row],[Notas Manuales]], “”, 0),"")} | R77: Beevana crema +Varicose veins x1 + Bee Venom BSWELL x1 + Beevana crema +Varicose veins x1 + Bee Venom BSWELL x1 | S77: 14911.5 | T77: -11990.8 | U77: {=IFERROR(_xlfn.IFS(tblPedidos[[#This Row],[estado_operativo]]="ENTREGADO",tblPedidos[[#This Row],[ganancia_calc]],tblPedidos[[#This Row],[estado_operativo]]="DEVOLUCION",tblPedidos[[#This Row],[costo_devolucion_estimado]]),0)} -> 0 | V77: 0 | W77: 54900 | X77: 14988.5 | Y77: 25000 | Z77: 46043 | AA77: 1 | AB77: 0.72430556 | AC77: EN BODEGA ORIGEN | AD77: EN BODEGA ORIGEN | AE77: ORIGEN
C78: 954 | D78: 63334522 | E78: 46042 | F78: Vanessa Osorio | G78: INTERRAPIDISIMO | J78: ORIGEN | K78: 240044572621 | L78: ANTIOQUIA | M78: GUARNE | N78: Cliente recoge pedido en oficina de Interrapidisimo en Guarne cliente recoge en esa oficina | O78: 3005962588 | P78: {=IFERROR(_xlfn.XLOOKUP(tblPedidos[[#This Row],[id_dropi]],tblNotas[[#This Row],[id__dropi]],tblNotas[[#This Row],[Notas Manuales]], “”, 0),"")} | Q78: PEDIDO PARA RECOGER EN OFICINA DE INTERRAPIDISIMO | R78: Quemador de grasa Lemme Burn 60 cáps x2 + Quemador de grasa Lemme Burn 60 cáps x2 | S78: 20654.5 | T78: -19245.5 | U78: {=IFERROR(_xlfn.IFS(tblPedidos[[#This Row],[estado_operativo]]="ENTREGADO",tblPedidos[[#This Row],[ganancia_calc]],tblPedidos[[#This Row],[estado_operativo]]="DEVOLUCION",tblPedidos[[#This Row],[costo_devolucion_estimado]]),0)} -> 0 | V78: 0 | W78: 89900 | X78: 19245.5 | Y78: 50000 | Z78: 46043 | AA78: 1 | AB78: 0.83958333 | AC78: ADMITIDA | AD78: ADMITIDA | AE78: ORIGEN
C79: 955 | D79: 63334195 | E79: 46042 | F79: Rosa Tapasco | G79: INTERRAPIDISIMO | J79: ORIGEN | K79: 240044597002 | L79: QUINDIO | M79: ARMENIA (Q) | N79: Barrio Alfonso López manzana E #15 | O79: 3053000506 | P79: {=IFERROR(_xlfn.XLOOKUP(tblPedidos[[#This Row],[id_dropi]],tblNotas[[#This Row],[id__dropi]],tblNotas[[#This Row],[Notas Manuales]], “”, 0),"")} | R79: DUO capilar ADIOS FRIZZ - 500ml x1 + DUO capilar ADIOS FRIZZ - 500ml x1 | S79: 32654.5 | T79: -13795.5 | U79: {=IFERROR(_xlfn.IFS(tblPedidos[[#This Row],[estado_operativo]]="ENTREGADO",tblPedidos[[#This Row],[ganancia_calc]],tblPedidos[[#This Row],[estado_operativo]]="DEVOLUCION",tblPedidos[[#This Row],[costo_devolucion_estimado]]),0)} -> 0 | V79: 0 | W79: 69900 | X79: 13795.5 | Y79: 23450 | Z79: 46043 | AA79: 1 | AB79: 0.60277778 | AC79: GUIA_GENERADA | AD79: GUIA_GENERADA | AE79: ORIGEN
C80: 950 | D80: 63334042 | E80: 46042 | F80: Diana Milena Rivas Rodríguez | G80: INTERRAPIDISIMO | J80: ORIGEN | K80: 240044597018 | L80: CAQUETA | M80: EL PAUJIL | N80: Cliente recoge pedido en oficina de Interrapidisimo en El Paujil cliente recoge en esa oficina | O80: 3239712805 | P80: {=IFERROR(_xlfn.XLOOKUP(tblPedidos[[#This Row],[id_dropi]],tblNotas[[#This Row],[id__dropi]],tblNotas[[#This Row],[Notas Manuales]], “”, 0),"")} | Q80: PEDIDO PARA RECOGER EN OFICINA DE INTERRAPIDISIMO | R80: DUO capilar ADIOS FRIZZ - 300 ml x1 + DUO capilar ADIOS FRIZZ - 300 ml x1 | S80: 22054.5 | T80: -17895.5 | U80: {=IFERROR(_xlfn.IFS(tblPedidos[[#This Row],[estado_operativo]]="ENTREGADO",tblPedidos[[#This Row],[ganancia_calc]],tblPedidos[[#This Row],[estado_operativo]]="DEVOLUCION",tblPedidos[[#This Row],[costo_devolucion_estimado]]),0)} -> 0 | V80: 0 | W80: 59900 | X80: 17895.5 | Y80: 19950 | Z80: 46043 | AA80: 1 | AB80: 0.60277778 | AC80: GUIA_GENERADA | AD80: GUIA_GENERADA | AE80: ORIGEN
C81: 951 | D81: 63333986 | E81: 46042 | F81: Honeida Bonilla | G81: ENVIA | J81: ORIGEN | K81: 014155841793 | L81: VALLE | M81: BUGA | N81: Calle 15 # 12 - 67 Barrio santa bárbara | O81: 3135660432 | P81: {=IFERROR(_xlfn.XLOOKUP(tblPedidos[[#This Row],[id_dropi]],tblNotas[[#This Row],[id__dropi]],tblNotas[[#This Row],[Notas Manuales]], “”, 0),"")} | R81: Cepillo Plancha Secador 2 en 1 Alisador x2 + Cepillo Plancha Secador 2 en 1 Alisador x2 | S81: 30211.5 | T81: -12710.8 | U81: {=IFERROR(_xlfn.IFS(tblPedidos[[#This Row],[estado_operativo]]="ENTREGADO",tblPedidos[[#This Row],[ganancia_calc]],tblPedidos[[#This Row],[estado_operativo]]="DEVOLUCION",tblPedidos[[#This Row],[costo_devolucion_estimado]]),0)} -> 0 | V81: 0 | W81: 74900 | X81: 15888.5 | Y81: 28800 | Z81: 46043 | AA81: 1 | AB81: 0.69722222 | AC81: PREPARADO PARA TRANSPORTADORA | AD81: PREPARADO PARA TRANSPORTADORA | AE81: ORIGEN
C82: 952 | D82: 63333936 | E82: 46042 | F82: Otilia dé Jesús ORTIZ TABORDA | G82: INTERRAPIDISIMO | J82: ORIGEN | K82: 240044572661 | L82: RISARALDA | M82: MISTRATO | N82: Cliente recoge pedido en oficina de Interrapidisimo en Mistrato cliente recoge en esa oficina | O82: 3104418765 | P82: {=IFERROR(_xlfn.XLOOKUP(tblPedidos[[#This Row],[id_dropi]],tblNotas[[#This Row],[id__dropi]],tblNotas[[#This Row],[Notas Manuales]], “”, 0),"")} | Q82: PEDIDO PARA RECOGER EN OFICINA DE INTERRAPIDISIMO | R82: Truly Soft Serve + T. Glazed Donut 60ml x1 + Truly Soft Serve + T. Glazed Donut 60ml x1 | S82: 21779.5 | T82: -18120.5 | U82: {=IFERROR(_xlfn.IFS(tblPedidos[[#This Row],[estado_operativo]]="ENTREGADO",tblPedidos[[#This Row],[ganancia_calc]],tblPedidos[[#This Row],[estado_operativo]]="DEVOLUCION",tblPedidos[[#This Row],[costo_devolucion_estimado]]),0)} -> 0 | V82: 0 | W82: 64900 | X82: 18120.5 | Y82: 25000 | Z82: 46043 | AA82: 1 | AB82: 0.83958333 | AC82: ADMITIDA | AD82: ADMITIDA | AE82: ORIGEN
C83: 956 | D83: 63333877 | E83: 46042 | F83: Rubiela Pulido | G83: INTERRAPIDISIMO | J83: ORIGEN | K83: 240044550432 | L83: CUNDINAMARCA | M83: MADRID | N83: Calle 4b #16-07, Prados de Madrid, frente de la empresa Corona. | O83: 3209360240 | P83: {=IFERROR(_xlfn.XLOOKUP(tblPedidos[[#This Row],[id_dropi]],tblNotas[[#This Row],[id__dropi]],tblNotas[[#This Row],[Notas Manuales]], “”, 0),"")} | Q83: numero adicional 3116702091 | R83: 2 Beevana y 1 Crema varicose veins x1 + Bee Venom BSWELL x1 + 2 Beevana y 1 Crema varicose veins x1 + Bee Venom BSWELL x1 | S83: 26504.5 | T83: -12395.5 | U83: {=IFERROR(_xlfn.IFS(tblPedidos[[#This Row],[estado_operativo]]="ENTREGADO",tblPedidos[[#This Row],[ganancia_calc]],tblPedidos[[#This Row],[estado_operativo]]="DEVOLUCION",tblPedidos[[#This Row],[costo_devolucion_estimado]]),0)} -> 0 | V83: 0 | W83: 69900 | X83: 12395.5 | Y83: 31000 | Z83: 46043 | AA83: 1 | AB83: 0.75486111 | AC83: ADMITIDA | AD83: ADMITIDA | AE83: ORIGEN
C84: 960 | D84: 63333813 | E84: 46042 | F84: Víctor Gil | G84: INTERRAPIDISIMO | J84: ORIGEN | K84: 240044550443 | L84: CUNDINAMARCA | M84: CHOCONTA | N84: Cliente recoge pedido en oficina de Interrapidisimo en Choconta cliente recoge en esa oficina | O84: 3118544339 | P84: {=IFERROR(_xlfn.XLOOKUP(tblPedidos[[#This Row],[id_dropi]],tblNotas[[#This Row],[id__dropi]],tblNotas[[#This Row],[Notas Manuales]], “”, 0),"")} | Q84: PEDIDO PARA RECOGER EN OFICINA DE INTERRAPIDISIMO | R84: Aceite de Batana x2 + Aceite de Batana x2 | S84: 31329.5 | T84: -13570.5 | U84: {=IFERROR(_xlfn.IFS(tblPedidos[[#This Row],[estado_operativo]]="ENTREGADO",tblPedidos[[#This Row],[ganancia_calc]],tblPedidos[[#This Row],[estado_operativo]]="DEVOLUCION",tblPedidos[[#This Row],[costo_devolucion_estimado]]),0)} -> 0 | V84: 0 | W84: 64900 | X84: 13570.5 | Y84: 20000 | Z84: 46043 | AA84: 1 | AB84: 0.34305556 | AC84: PREPARADO PARA TRANSPORTADORA | AD84: PREPARADO PARA TRANSPORTADORA | AE84: ORIGEN
C85: 961 | D85: 63333568 | E85: 46042 | F85: Mavel Vinazco | G85: ENVIA | J85: TRANSITO | K85: 054014221442 | L85: VALLE | M85: PRADERA | N85: Calle 10 #13-42 segundo piso | O85: 3102017033 | P85: {=IFERROR(_xlfn.XLOOKUP(tblPedidos[[#This Row],[id_dropi]],tblNotas[[#This Row],[id__dropi]],tblNotas[[#This Row],[Notas Manuales]], “”, 0),"")} | R85: DUO capilar ADIOS FRIZZ - 500ml x1 + DUO capilar ADIOS FRIZZ - 500ml x1 | S85: 30786.5 | T85: -12530.8 | U85: {=IFERROR(_xlfn.IFS(tblPedidos[[#This Row],[estado_operativo]]="ENTREGADO",tblPedidos[[#This Row],[ganancia_calc]],tblPedidos[[#This Row],[estado_operativo]]="DEVOLUCION",tblPedidos[[#This Row],[costo_devolucion_estimado]]),0)} -> 0 | V85: 0 | W85: 69900 | X85: 15663.5 | Y85: 23450 | Z85: 46043 | AA85: 1 | AB85: 0.84930556 | AC85: EN BODEGA ORIGEN | AD85: DESPACHADA | AE85: TRANSITO
C86: 962 | D86: 63333466 | E86: 46042 | F86: Luz Fanny López | G86: INTERRAPIDISIMO | J86: ORIGEN | K86: 240044572672 | L86: ANTIOQUIA | M86: LA ESTRELLA | N86: Carrera 50 # 99 sur -69 Bosque de sauces, La tablaza | O86: 3135931826 | P86: {=IFERROR(_xlfn.XLOOKUP(tblPedidos[[#This Row],[id_dropi]],tblNotas[[#This Row],[id__dropi]],tblNotas[[#This Row],[Notas Manuales]], “”, 0),"")} | R86: Truly Soft Serve MINI 60ml x1 + Truly Soft Serve MINI 60ml x1 | S86: 26779.5 | T86: -13120.5 | U86: {=IFERROR(_xlfn.IFS(tblPedidos[[#This Row],[estado_operativo]]="ENTREGADO",tblPedidos[[#This Row],[ganancia_calc]],tblPedidos[[#This Row],[estado_operativo]]="DEVOLUCION",tblPedidos[[#This Row],[costo_devolucion_estimado]]),0)} -> 0 | V86: 0 | W86: 54900 | X86: 13120.5 | Y86: 15000 | Z86: 46043 | AA86: 1 | AB86: 0.83958333 | AC86: ADMITIDA | AD86: ADMITIDA | AE86: ORIGEN
C87: 957 | D87: 63333423 | E87: 46042 | F87: Marleidys Mendoza | G87: INTERRAPIDISIMO | J87: ORIGEN | K87: 240044552806 | L87: ANTIOQUIA | M87: SAN JUAN DE URABA | N87: OFICINA INTERRAPIDISIMO SAN JUAN DE URABA | O87: 3025768990 | P87: {=IFERROR(_xlfn.XLOOKUP(tblPedidos[[#This Row],[id_dropi]],tblNotas[[#This Row],[id__dropi]],tblNotas[[#This Row],[Notas Manuales]], “”, 0),"")} | Q87: CLIENTE RECLAMA EN OFICINA INTERRAPIDISIMO SAN JUAN DE URABA | R87: Cepillo Plancha Secador 2 en 1 Alisador x1 + Cepillo Plancha Secador 2 en 1 Alisador x1 | S87: 16801 | T87: -18699 | U87: {=IFERROR(_xlfn.IFS(tblPedidos[[#This Row],[estado_operativo]]="ENTREGADO",tblPedidos[[#This Row],[ganancia_calc]],tblPedidos[[#This Row],[estado_operativo]]="DEVOLUCION",tblPedidos[[#This Row],[costo_devolucion_estimado]]),0)} -> 0 | V87: 0 | W87: 49900 | X87: 18699 | Y87: 14400 | Z87: 46043 | AA87: 1 | AB87: 0.70347222 | AC87: PREPARADO PARA TRANSPORTADORA | AD87: PREPARADO PARA TRANSPORTADORA | AE87: ORIGEN
C88: 958 | D88: 63333231 | E88: 46042 | F88: ADRIANA PATRICIA ASPRIELLA PEÑA | G88: INTERRAPIDISIMO | J88: ORIGEN | K88: 240044597030 | L88: SANTANDER | M88: BUCARAMANGA | N88: CARRERA 20 #59A-04 BARRIO LA TRINIDAD FLORIDA BLANCA | O88: 3168952028 | P88: {=IFERROR(_xlfn.XLOOKUP(tblPedidos[[#This Row],[id_dropi]],tblNotas[[#This Row],[id__dropi]],tblNotas[[#This Row],[Notas Manuales]], “”, 0),"")} | R88: DUO capilar ADIOS FRIZZ - 300 ml x1 + DUO capilar ADIOS FRIZZ - 300 ml x1 | S88: 22054.5 | T88: -17895.5 | U88: {=IFERROR(_xlfn.IFS(tblPedidos[[#This Row],[estado_operativo]]="ENTREGADO",tblPedidos[[#This Row],[ganancia_calc]],tblPedidos[[#This Row],[estado_operativo]]="DEVOLUCION",tblPedidos[[#This Row],[costo_devolucion_estimado]]),0)} -> 0 | V88: 0 | W88: 59900 | X88: 17895.5 | Y88: 19950 | Z88: 46043 | AA88: 1 | AB88: 0.60277778 | AC88: GUIA_GENERADA | AD88: GUIA_GENERADA | AE88: ORIGEN
C89: 959 | D89: 63333116 | E89: 46042 | F89: Fernanda Gómez | G89: INTERRAPIDISIMO | J89: ORIGEN | K89: 240044572686 | L89: CUNDINAMARCA | M89: BOGOTA | N89: Carrera 98 # 17-35 | O89: 3022231626 | P89: {=IFERROR(_xlfn.XLOOKUP(tblPedidos[[#This Row],[id_dropi]],tblNotas[[#This Row],[id__dropi]],tblNotas[[#This Row],[Notas Manuales]], “”, 0),"")} | R89: Truly Soft Serve MINI 60ml x2 + Truly Soft Serve MINI 60ml x2 | S89: 21554.5 | T89: -18345.5 | U89: {=IFERROR(_xlfn.IFS(tblPedidos[[#This Row],[estado_operativo]]="ENTREGADO",tblPedidos[[#This Row],[ganancia_calc]],tblPedidos[[#This Row],[estado_operativo]]="DEVOLUCION",tblPedidos[[#This Row],[costo_devolucion_estimado]]),0)} -> 0 | V89: 0 | W89: 69900 | X89: 18345.5 | Y89: 30000 | Z89: 46043 | AA89: 1 | AB89: 0.83958333 | AC89: ADMITIDA | AD89: ADMITIDA | AE89: ORIGEN
C90: 976 | D90: 63332891 | E90: 46042 | F90: Yury Maritza García Castañeda | G90: INTERRAPIDISIMO | J90: ORIGEN | K90: 240044597035 | L90: CUNDINAMARCA | M90: FUNZA | N90: Calle 20 #7b-66 Bellisca, casa de barrio | O90: 3213391284 | P90: {=IFERROR(_xlfn.XLOOKUP(tblPedidos[[#This Row],[id_dropi]],tblNotas[[#This Row],[id__dropi]],tblNotas[[#This Row],[Notas Manuales]], “”, 0),"")} | R90: DUO capilar ADIOS FRIZZ - 500ml x1 + DUO capilar ADIOS FRIZZ - 500ml x1 | S90: 28104.5 | T90: -18345.5 | U90: {=IFERROR(_xlfn.IFS(tblPedidos[[#This Row],[estado_operativo]]="ENTREGADO",tblPedidos[[#This Row],[ganancia_calc]],tblPedidos[[#This Row],[estado_operativo]]="DEVOLUCION",tblPedidos[[#This Row],[costo_devolucion_estimado]]),0)} -> 0 | V90: 0 | W90: 69900 | X90: 18345.5 | Y90: 23450 | Z90: 46043 | AA90: 1 | AB90: 0.60277778 | AC90: GUIA_GENERADA | AD90: GUIA_GENERADA | AE90: ORIGEN
C91: 993 | D91: 63332799 | E91: 46042 | F91: Alejandra Mejia | G91: ENVIA | J91: ORIGEN | K91: 024032305867 | L91: VALLE | M91: VILLA GORGONA | N91: Carrera 7G oeste # 22-59, Dalias sector - 5 | O91: 3135047261 | P91: {=IFERROR(_xlfn.XLOOKUP(tblPedidos[[#This Row],[id_dropi]],tblNotas[[#This Row],[id__dropi]],tblNotas[[#This Row],[Notas Manuales]], “”, 0),"")} | R91: Truly Soft Serve MINI 60ml x1 + Truly Soft Serve MINI 60ml x1 | S91: 28367.5 | T91: -9226 | U91: {=IFERROR(_xlfn.IFS(tblPedidos[[#This Row],[estado_operativo]]="ENTREGADO",tblPedidos[[#This Row],[ganancia_calc]],tblPedidos[[#This Row],[estado_operativo]]="DEVOLUCION",tblPedidos[[#This Row],[costo_devolucion_estimado]]),0)} -> 0 | V91: 0 | W91: 54900 | X91: 11532.5 | Y91: 15000 | Z91: 46043 | AA91: 1 | AB91: 0.91180556 | AC91: EN BODEGA ORIGEN | AD91: EN BODEGA ORIGEN | AE91: ORIGEN
C92: 994 | D92: 63332662 | E92: 46042 | F92: Maria de los ángeles perez morales | G92: INTERRAPIDISIMO | J92: ORIGEN | K92: 240044597042 | L92: BOYACA | M92: SANTA SOFIA | N92: Cliente recoge pedido en oficina de Interrapidisimo en Santa Sofia cliente recoge en esa oficina | O92: 3202741468 | P92: {=IFERROR(_xlfn.XLOOKUP(tblPedidos[[#This Row],[id_dropi]],tblNotas[[#This Row],[id__dropi]],tblNotas[[#This Row],[Notas Manuales]], “”, 0),"")} | Q92: PEDIDO PARA RECOGER EN OFICINA DE INTERRAPIDISIMO | R92: DUO capilar ADIOS FRIZZ - 300 ml x1 + DUO capilar ADIOS FRIZZ - 300 ml x1 | S92: 22054.5 | T92: -17895.5 | U92: {=IFERROR(_xlfn.IFS(tblPedidos[[#This Row],[estado_operativo]]="ENTREGADO",tblPedidos[[#This Row],[ganancia_calc]],tblPedidos[[#This Row],[estado_operativo]]="DEVOLUCION",tblPedidos[[#This Row],[costo_devolucion_estimado]]),0)} -> 0 | V92: 0 | W92: 59900 | X92: 17895.5 | Y92: 19950 | Z92: 46043 | AA92: 1 | AB92: 0.60277778 | AC92: GUIA_GENERADA | AD92: GUIA_GENERADA | AE92: ORIGEN
C93: 995 | D93: 63332504 | E93: 46042 | F93: Jenny Acevedo | G93: INTERRAPIDISIMO | J93: ORIGEN | K93: 240044552843 | L93: CUNDINAMARCA | M93: LA CALERA | N93: OFICINA INTERRAPIDISIMO LA CALERA | O93: 3244268685 | P93: {=IFERROR(_xlfn.XLOOKUP(tblPedidos[[#This Row],[id_dropi]],tblNotas[[#This Row],[id__dropi]],tblNotas[[#This Row],[Notas Manuales]], “”, 0),"")} | Q93: CLIENTE RECLAMA EN OFICINA INTERRAPIDISIMO LA CALERA | R93: Cepillo Plancha Secador 2 en 1 Alisador x2 + Cepillo Plancha Secador 2 en 1 Alisador x2 | S93: 28704.5 | T93: -12395.5 | U93: {=IFERROR(_xlfn.IFS(tblPedidos[[#This Row],[estado_operativo]]="ENTREGADO",tblPedidos[[#This Row],[ganancia_calc]],tblPedidos[[#This Row],[estado_operativo]]="DEVOLUCION",tblPedidos[[#This Row],[costo_devolucion_estimado]]),0)} -> 0 | V93: 0 | W93: 69900 | X93: 12395.5 | Y93: 28800 | Z93: 46043 | AA93: 1 | AB93: 0.70347222 | AC93: PREPARADO PARA TRANSPORTADORA | AD93: PREPARADO PARA TRANSPORTADORA | AE93: ORIGEN
C94: 990 | D94: 63332270 | E94: 46042 | F94: Luz Mery Hernández Restrepo | G94: INTERRAPIDISIMO | J94: ORIGEN | K94: 240044552849 | L94: CAQUETA | M94: CARTAGENA DEL CHAIRA | N94: OFICINA INTERRAPIDISIMO CARTAGENA DE CHAIRA | O94: 3208206881 | P94: {=IFERROR(_xlfn.XLOOKUP(tblPedidos[[#This Row],[id_dropi]],tblNotas[[#This Row],[id__dropi]],tblNotas[[#This Row],[Notas Manuales]], “”, 0),"")} | Q94: CLIENTE RECLAMA OFICINA INTERRAPIDISIMO CARTAGENA DE CHAIRA | R94: Cepillo Plancha Secador 2 en 1 Alisador x1 + Cepillo Plancha Secador 2 en 1 Alisador x1 | S94: 22829.5 | T94: -17670.5 | U94: {=IFERROR(_xlfn.IFS(tblPedidos[[#This Row],[estado_operativo]]="ENTREGADO",tblPedidos[[#This Row],[ganancia_calc]],tblPedidos[[#This Row],[estado_operativo]]="DEVOLUCION",tblPedidos[[#This Row],[costo_devolucion_estimado]]),0)} -> 0 | V94: 0 | W94: 54900 | X94: 17670.5 | Y94: 14400 | Z94: 46043 | AA94: 1 | AB94: 0.70347222 | AC94: PREPARADO PARA TRANSPORTADORA | AD94: PREPARADO PARA TRANSPORTADORA | AE94: ORIGEN
C95: 991 | D95: 63331823 | E95: 46042 | F95: Karina Avila Lambertino | G95: INTERRAPIDISIMO | J95: ORIGEN | K95: 240044552861 | L95: CORDOBA | M95: MOÑITOS | N95: OFICINA INTERRAPIDISIMO MOÑITOS CORDOBA | O95: 3205453445 | P95: {=IFERROR(_xlfn.XLOOKUP(tblPedidos[[#This Row],[id_dropi]],tblNotas[[#This Row],[id__dropi]],tblNotas[[#This Row],[Notas Manuales]], “”, 0),"")} | Q95: CLIENTE RECLAMA EN OFICINA INTERRAPIDISIMO MOÑITOS CORDOBA | R95: Cepillo Plancha Secador 2 en 1 Alisador x1 + Cepillo Plancha Secador 2 en 1 Alisador x1 | S95: 22829.5 | T95: -17670.5 | U95: {=IFERROR(_xlfn.IFS(tblPedidos[[#This Row],[estado_operativo]]="ENTREGADO",tblPedidos[[#This Row],[ganancia_calc]],tblPedidos[[#This Row],[estado_operativo]]="DEVOLUCION",tblPedidos[[#This Row],[costo_devolucion_estimado]]),0)} -> 0 | V95: 0 | W95: 54900 | X95: 17670.5 | Y95: 14400 | Z95: 46043 | AA95: 1 | AB95: 0.70347222 | AC95: PREPARADO PARA TRANSPORTADORA | AD95: PREPARADO PARA TRANSPORTADORA | AE95: ORIGEN
C96: 992 | D96: 63331315 | E96: 46042 | F96: Elizamar cortes | G96: ENVIA | J96: ORIGEN | K96: 014155841858 | L96: VALLE | M96: CALI | N96: Cra 26P 9 # 87 - 25 Barrio marroquí ll | O96: 3151004816 | P96: {=IFERROR(_xlfn.XLOOKUP(tblPedidos[[#This Row],[id_dropi]],tblNotas[[#This Row],[id__dropi]],tblNotas[[#This Row],[Notas Manuales]], “”, 0),"")} | Q96: Cra 26P 9 # 87 - 25 Barrio marroquí ll | R96: Cepillo Plancha Secador 2 en 1 Alisador x1 + Cepillo Plancha Secador 2 en 1 Alisador x1 | S96: 20736.5 | T96: -11810.8 | U96: {=IFERROR(_xlfn.IFS(tblPedidos[[#This Row],[estado_operativo]]="ENTREGADO",tblPedidos[[#This Row],[ganancia_calc]],tblPedidos[[#This Row],[estado_operativo]]="DEVOLUCION",tblPedidos[[#This Row],[costo_devolucion_estimado]]),0)} -> 0 | V96: 0 | W96: 49900 | X96: 14763.5 | Y96: 14400 | Z96: 46043 | AA96: 1 | AB96: 0.69722222 | AC96: PREPARADO PARA TRANSPORTADORA | AD96: PREPARADO PARA TRANSPORTADORA | AE96: ORIGEN
C97: 996 | D97: 63330825 | E97: 46042 | F97: Ana Milena Cotrina | G97: INTERRAPIDISIMO | J97: ORIGEN | K97: 240044552924 | L97: CUNDINAMARCA | M97: SASAIMA | N97: OFICINA PRINCIPAL INTERRAPIDISIMO SASAIMA | O97: 3134042749 | P97: {=IFERROR(_xlfn.XLOOKUP(tblPedidos[[#This Row],[id_dropi]],tblNotas[[#This Row],[id__dropi]],tblNotas[[#This Row],[Notas Manuales]], “”, 0),"")} | Q97: CLIENTE RECLAMA OFICINA PRINCIPAL INTERRAPIDISIMO SASAIMA | R97: Cepillo Plancha Secador 2 en 1 Alisador x1 + Cepillo Plancha Secador 2 en 1 Alisador x1 | S97: 27379.5 | T97: -13120.5 | U97: {=IFERROR(_xlfn.IFS(tblPedidos[[#This Row],[estado_operativo]]="ENTREGADO",tblPedidos[[#This Row],[ganancia_calc]],tblPedidos[[#This Row],[estado_operativo]]="DEVOLUCION",tblPedidos[[#This Row],[costo_devolucion_estimado]]),0)} -> 0 | V97: 0 | W97: 54900 | X97: 13120.5 | Y97: 14400 | Z97: 46043 | AA97: 1 | AB97: 0.70347222 | AC97: PREPARADO PARA TRANSPORTADORA | AD97: PREPARADO PARA TRANSPORTADORA | AE97: ORIGEN
C98: 1000 | D98: 63330165 | E98: 46042 | F98: Glenis Machuca Aldana | G98: INTERRAPIDISIMO | J98: ORIGEN | K98: 240044552938 | L98: ANTIOQUIA | M98: TURBO | N98: Carrera 54 #48-108 Barrio Turbay Ayala | O98: 3134847655 | P98: {=IFERROR(_xlfn.XLOOKUP(tblPedidos[[#This Row],[id_dropi]],tblNotas[[#This Row],[id__dropi]],tblNotas[[#This Row],[Notas Manuales]], “”, 0),"")} | Q98: Barrio Turbay Ayala | R98: Cepillo Plancha Secador 2 en 1 Alisador x2 + Cepillo Plancha Secador 2 en 1 Alisador x2 | S98: 27529.5 | T98: -18570.5 | U98: {=IFERROR(_xlfn.IFS(tblPedidos[[#This Row],[estado_operativo]]="ENTREGADO",tblPedidos[[#This Row],[ganancia_calc]],tblPedidos[[#This Row],[estado_operativo]]="DEVOLUCION",tblPedidos[[#This Row],[costo_devolucion_estimado]]),0)} -> 0 | V98: 0 | W98: 74900 | X98: 18570.5 | Y98: 28800 | Z98: 46043 | AA98: 1 | AB98: 0.70347222 | AC98: PREPARADO PARA TRANSPORTADORA | AD98: PREPARADO PARA TRANSPORTADORA | AE98: ORIGEN
C99: 1001 | D99: 63329510 | E99: 46042 | F99: Mónica Pareja | G99: ENVIA | J99: ORIGEN | K99: 014155841877 | L99: VALLE | M99: CALI | N99: Calle 4 #27-79, Barrio San Fernando | O99: 3183664278 | P99: {=IFERROR(_xlfn.XLOOKUP(tblPedidos[[#This Row],[id_dropi]],tblNotas[[#This Row],[id__dropi]],tblNotas[[#This Row],[Notas Manuales]], “”, 0),"")} | Q99: Barrio San Fernando | R99: Cepillo Plancha Secador 2 en 1 Alisador x1 + Cepillo Plancha Secador 2 en 1 Alisador x1 | S99: 25511.5 | T99: -11990.8 | U99: {=IFERROR(_xlfn.IFS(tblPedidos[[#This Row],[estado_operativo]]="ENTREGADO",tblPedidos[[#This Row],[ganancia_calc]],tblPedidos[[#This Row],[estado_operativo]]="DEVOLUCION",tblPedidos[[#This Row],[costo_devolucion_estimado]]),0)} -> 0 | V99: 0 | W99: 54900 | X99: 14988.5 | Y99: 14400 | Z99: 46043 | AA99: 1 | AB99: 0.69722222 | AC99: PREPARADO PARA TRANSPORTADORA | AD99: PREPARADO PARA TRANSPORTADORA | AE99: ORIGEN
C100: 1002 | D100: 63328359 | E100: 46042 | F100: Saidy Hernández | G100: ENVIA | J100: ORIGEN | K100: 024032305872 | L100: ANTIOQUIA | M100: MEDELLIN | N100: Carrera 143 #64 - 26 interior 103, San Cristobal, Palenque | O100: 3146396628 | P100: {=IFERROR(_xlfn.XLOOKUP(tblPedidos[[#This Row],[id_dropi]],tblNotas[[#This Row],[id__dropi]],tblNotas[[#This Row],[Notas Manuales]], “”, 0),"")} | R100: Quemador de grasa Lemme Burn 60 cáps x2 + Quemador de grasa Lemme Burn 60 cáps x2 | S100: 23336.5 | T100: -13250.8 | U100: {=IFERROR(_xlfn.IFS(tblPedidos[[#This Row],[estado_operativo]]="ENTREGADO",tblPedidos[[#This Row],[ganancia_calc]],tblPedidos[[#This Row],[estado_operativo]]="DEVOLUCION",tblPedidos[[#This Row],[costo_devolucion_estimado]]),0)} -> 0 | V100: 0 | W100: 89900 | X100: 16563.5 | Y100: 50000 | Z100: 46043 | AA100: 1 | AB100: 0.91180556 | AC100: EN BODEGA ORIGEN | AD100: EN BODEGA ORIGEN | AE100: ORIGEN
...

Sheet NOTAS
A1: id__dropi | B1: Nombre | C1: telefono | D1: Producto | E1: Oficina | F1: Notas Manuales
A2: 61322803 | B2: =VLOOKUP(tblNotas[[#This Row],[id__dropi]],Pedidos!D:O,5,0) -> #N/A | C2: =VLOOKUP(tblNotas[[#This Row],[id__dropi]],Pedidos!D:O,12,0) -> #N/A | F2: llamado 3 veces
A3: 61584447 | B3: =VLOOKUP(tblNotas[[#This Row],[id__dropi]],Pedidos!D:O,5,0) -> #N/A | C3: =VLOOKUP(tblNotas[[#This Row],[id__dropi]],Pedidos!D:O,12,0) -> #N/A | F3: llame 10 veces
A4: 61687973 | B4: =VLOOKUP(tblNotas[[#This Row],[id__dropi]],Pedidos!D:O,5,0) -> 0 | C4: =VLOOKUP(tblNotas[[#This Row],[id__dropi]],Pedidos!D:O,12,0) -> 3128387983 | F4: llame 10 veces
A5: 61716971 | B5: =VLOOKUP(tblNotas[[#This Row],[id__dropi]],Pedidos!D:O,5,0) -> 0 | C5: =VLOOKUP(tblNotas[[#This Row],[id__dropi]],Pedidos!D:O,12,0) -> 3043681389
A6: 61715914 | B6: =VLOOKUP(tblNotas[[#This Row],[id__dropi]],Pedidos!D:O,5,0) -> 0 | C6: =VLOOKUP(tblNotas[[#This Row],[id__dropi]],Pedidos!D:O,12,0) -> 3122504723
A7: 61683459 | B7: =VLOOKUP(tblNotas[[#This Row],[id__dropi]],Pedidos!D:O,5,0) -> 0 | C7: =VLOOKUP(tblNotas[[#This Row],[id__dropi]],Pedidos!D:O,12,0) -> 3125206068
A8: 61808621 | B8: =VLOOKUP(tblNotas[[#This Row],[id__dropi]],Pedidos!D:O,5,0) -> 0 | C8: =VLOOKUP(tblNotas[[#This Row],[id__dropi]],Pedidos!D:O,12,0) -> 3116739503
A9: 61808234 | B9: =VLOOKUP(tblNotas[[#This Row],[id__dropi]],Pedidos!D:O,5,0) -> 0 | C9: =VLOOKUP(tblNotas[[#This Row],[id__dropi]],Pedidos!D:O,12,0) -> 3205381934
A10: 61788521 | B10: =VLOOKUP(tblNotas[[#This Row],[id__dropi]],Pedidos!D:O,5,0) -> 0 | C10: =VLOOKUP(tblNotas[[#This Row],[id__dropi]],Pedidos!D:O,12,0) -> 3242038699
A11: 61935012 | B11: =VLOOKUP(tblNotas[[#This Row],[id__dropi]],Pedidos!D:O,5,0) -> 0 | C11: =VLOOKUP(tblNotas[[#This Row],[id__dropi]],Pedidos!D:O,12,0) -> 3007515120
A12: 61884335 | B12: =VLOOKUP(tblNotas[[#This Row],[id__dropi]],Pedidos!D:O,5,0) -> 0 | C12: =VLOOKUP(tblNotas[[#This Row],[id__dropi]],Pedidos!D:O,12,0) -> 3113614112
A13: 62055562 | B13: =VLOOKUP(tblNotas[[#This Row],[id__dropi]],Pedidos!D:O,5,0) -> 0 | C13: =VLOOKUP(tblNotas[[#This Row],[id__dropi]],Pedidos!D:O,12,0) -> 3017501313
A14: 62054687 | B14: =VLOOKUP(tblNotas[[#This Row],[id__dropi]],Pedidos!D:O,5,0) -> 0 | C14: =VLOOKUP(tblNotas[[#This Row],[id__dropi]],Pedidos!D:O,12,0) -> 3247119922
A15: 62174626 | B15: =VLOOKUP(tblNotas[[#This Row],[id__dropi]],Pedidos!D:O,5,0) -> 0 | C15: =VLOOKUP(tblNotas[[#This Row],[id__dropi]],Pedidos!D:O,12,0) -> 3136242428
A16: 62172963 | B16: =VLOOKUP(tblNotas[[#This Row],[id__dropi]],Pedidos!D:O,5,0) -> 0 | C16: =VLOOKUP(tblNotas[[#This Row],[id__dropi]],Pedidos!D:O,12,0) -> 3123347964
... A71: 63102169 | B71: =VLOOKUP(tblNotas[[#This Row],[id__dropi]],Pedidos!D:O,5,0) -> 0 | C71: =VLOOKUP(tblNotas[[#This Row],[id__dropi]],Pedidos!D:O,12,0) -> 3203916924

Sheet Mapeo_Estados
A1: Mapeo de estados (Dropi/Transportadoras) → tus estados
A3: transportadora (opcional) | B3: estatus_original | C3: ultimo_movimiento (opcional) | D3: estado_unificado | F3: Estados estándar
B4: ANULADO | D4: ANULADO | F4: PENDIENTE | I4: estatus_original
B5: CANCELADO | D5: CANCELADO | F5: ORIGEN | I5: estado_unificado
B6: EN BODEGA DESTINO | D6: DESTINO | F6: TRÁNSITO
B7: DEVOLUCION | D7: DEVOLUCION | F7: DESTINO
B8: ENTREGADO | D8: ENTREGADO | F8: REPARTO
B9: NOVEDAD | D9: NOVEDAD | F9: ENTREGADO
B10: NOVEDAD SOLUCIONADA | D10: NOVEDAD SOLUCIONADA | F10: DEVOLUCIÓN
B11: OFICINA | D11: OFICINA | F11: NOVEDAD
B12: RECLAME EN OFICINA | D12: OFICINA | F12: NOVEDAD SOLUCIONADA
B13: GUIA_GENERADA | D13: ORIGEN | F13: OFICINA
B14: GUIA_GENERADA | D14: ORIGEN | F14: OFICINA 1
B15: PREPARADO PARA TRANSPORTADORA | D15: ORIGEN | F15: CANCELADO
B16: PENDIENTE | D16: PENDIENTE | F16: SINIESTRO / EXTRAVIADO
B17: EN RUTA | D17: REPARTO
B18: EN REPARTO | D18: REPARTO
B19: INTENTO DE ENTREGA | D19: REPARTO
B20: EN RUTA | D20: REPARTO
B21: EN REPARTO | D21: REPARTO
B22: DESPACHADA | D22: TRANSITO
B23: EN BODEGA TRANSPORTADORA | D23: TRANSITO
B24: PENDIENTE | D24: PENDIENTE
B25: PENDIENTE CONFIRMACION
B26: PENDIENTE
B27: GUIA_GENERADA | D27: ORIGEN
B28: GUIA_ANULADA | D28: CANCELADO
B29: CANCELADO
B30: RECHAZADO | D30: CANCELADO
B31: ENTREGADO
B32: DEVOLUCION
B33: NOVEDAD SOLUCIONADA
B34: PREPARADO PARA TRANSPORTADORA
B35: INDEMNIZADA POR DROPI
B36: DEVOLUCION EN TRANSITO
B37: ENTREGADO A TRANSPORTADORA | D37: ORIGEN
B38: EN BODEGA DROPI | D38: ORIGEN
B39: RECOGIDO POR DROPI | D39: ORIGEN
B40: RECIBIDO PAU
B41: RECIBIDO DEL CLIENTE
B42: EN PROCESAMIENTO | D42: ORIGEN
B43: EN SALIDA DE CIUDAD INTERMEDIA
B44: ENTRADA BODEGA LOCAL
B45: EN TRANSITO EN CIUDAD INTERMEDIA
B46: ENTREGA VERIFICADA
B47: ENVIO PARA ENTREGA A DOMICILIO
B48: ENVIO PARA ENTREGA EN OFICINA
B49: ENVIO REVERSADO A BODEGA LOCAL
B50: ENVIO TRASLADADO A MANIFIESTO
B51: EN ZONA DE DISTRIBUCION
B52: SINIESTRADO
B53: SALIO A CIUDAD DESTINO
B54: SALIDA A BODEGA LOCAL
... B61: INGRESO AL CENTRO LOGISTICO
B62: SIN MOVIMIENTOS | D62: SIN MOVIMIENTO
B63: GENERADA
B64: PRODUCIDA
B65: ANULADA
B66: DESPACHADA
B67: EN BODEGA DESTINO
B68: EN REPARTO
B69: ENTREGADA
B70: NOVEDAD
B71: NO TRANSMITIDA
B72: EN PROCESO DE INDEMNIZACION
B73: INDEMNIZADA
B74: ENTREGADA DIGITALIZADA
B75: EN TRANSITO | D75: TRANSITO
B76: DESPACHADA DE TRANSITO
B77: EN ESPERA DE RX | D77: TRANSITO
B78: EN REEXPEDICION
B79: EN ESPERA DE RUTA DOMESTICA | D79: DESTINO
B80: EN ESPERA DE CITA
B81: CITA PROGRAMADA
B82: SOLUCIONADA EN MALLA
B83: ORIGEN DOMESTICO EN ESPERA DE DESPACHO NACIONAL
B84: MERCANCIA RECOGIDA
B85: STAND BY
B86: DESTRUCCION - SALVAMENTO - DONACION
B87: REZAGO
B88: DEVOLUCION PARCIAL | D88: DEVOLUCION
B89: REDIRECCIONADO
B90: ENTREGADA CON OBSERVACION
B91: DEVUELTA
B92: GUIA NO EXISTE
B93: A RECIBIR POR COORDINADORA
B94: EN TERMINAL ORIGEN
B95: EN TRANSPORTE
B96: EN TERMINAL DESTINO
B97: CERRADO POR INCIDENCIA, VER CAUSA
B98: EN PUNTO DROOP
B99: ENVÍO ADMITIDO
B100: INGRESADO A BODEGA
... B104: EN DISTRIBUCIÓN URBANA
B105: EN PROCESO DE DEVOLUCIÓN | D105: DEVOLUCION
B106: EN CONFIRMACIÓN TELEFÓNICA
B107: DEVUELTO AL REMITENTE
B108: ENTREGA EXITOSA
B109: PARA NUEVO INTENTO ENTREGA
B110: PRUEBA DE ENTREGA DIGITALIZADA
...

Sheet Dashboard_Pro
A1: Dropi • Dashboard PRO | K1: Actualizado: | L1: =TODAY() -> 46047
B4: Pedidos (Total) | F4: Entregados | J4: Devoluciones
B5: =ROWS(tblPedidos[id_dropi]) -> 1064 | F5: =COUNTIFS(tblPedidos[estado_operativo],"ENTREGADO") -> 567 | J5: =COUNTIFS(tblPedidos[estado_operativo],"DEVOL*") -> 54
B6: Datos → Actualizar todo | F6: Datos → Actualizar todo | J6: Datos → Actualizar todo
B8: % Devolución | F8: Pendientes | J8: Novedad
B9: =IFERROR(COUNTIFS(tblPedidos[estado_operativo],"DEVOL*")/ROWS(tblPedidos[id_dropi]),0) -> 0.05075188 | F9: =MAX(0, ROWS(tblPedidos[id_dropi]) - COUNTIFS(tblPedidos[estado_operativo],"ENTREG*") - COUNTIFS(tblPedidos[estado_operativo],"DEVOL*") - COUNTIFS(tblPedidos[estado_operativo],"CANCEL*") - COUNTIFS(tblPedidos[estado_operativo],"ANUL*") ) -> 425 | J9: =COUNTIFS(tblPedidos[estado_operativo],"NOVEDAD*") -> 33
B10: Datos → Actualizar todo | F10: Datos → Actualizar todo | J10: Datos → Actualizar todo
B12: Costo devoluciones | F12: Ganancia total | J12: Ventas total
B13: =IFERROR(SUMIFS(tblPedidos[costo_devolucion_estimado],tblPedidos[estado_operativo],"DEVOLUCIÓN"),0) -> 0 | F13: =SUM((tblPedidos[cartera_aplicada])) -> 53491532 | J13: =IFERROR(SUM(#REF!),0) -> 0
B14: Datos → Actualizar todo | F14: Datos → Actualizar todo | J14: Datos → Actualizar todo
B16: Distribución por estado | F16: Devolución por transportadora
B17: Estado | C17: Pedidos | F17: Transportadora | G17: Pedidos | H17: Entregados | I17: Devolución | J17: % Devol. | K17: % Entr
B18: PENDIENTE | C18: =IFERROR(COUNTIFS(tblPedidos[estado_operativo],B18),0) -> 62 | F18: ENVIA | G18: =COUNTIFS(tblPedidos[transportadora],tblTransportadora[[#This Row],[Transportadora]]) -> 259 | H18: =COUNTIFS(tblPedidos[transportadora],tblTransportadora[[#This Row],[Transportadora]],tblPedidos[estado_operativo],"ENTREGADO") -> 135 | I18: =COUNTIFS(tblPedidos[transportadora],tblTransportadora[[#This Row],[Transportadora]],tblPedidos[estado_operativo],"DEVOLUCION") -> 6 | J18: =IFERROR(tblTransportadora[[#This Row],[Devolución]]/tblTransportadora[[#This Row],[Pedidos]],0) -> 0.023166023 | K18: =IFERROR(tblTransportadora[[#This Row],[Entregados]]/tblTransportadora[[#This Row],[Pedidos]],0) -> 0.52123552
B19: ORIGEN | C19: =IFERROR(COUNTIFS(tblPedidos[estado_operativo],B19),0) -> 136 | F19: INTERRAPIDISIMO | G19: =COUNTIFS(tblPedidos[transportadora],tblTransportadora[[#This Row],[Transportadora]]) -> 775 | H19: =COUNTIFS(tblPedidos[transportadora],tblTransportadora[[#This Row],[Transportadora]],tblPedidos[estado_operativo],"ENTREGADO") -> 416 | I19: =COUNTIFS(tblPedidos[transportadora],tblTransportadora[[#This Row],[Transportadora]],tblPedidos[estado_operativo],"DEVOLUCION") -> 45 | J19: =IFERROR(tblTransportadora[[#This Row],[Devolución]]/tblTransportadora[[#This Row],[Pedidos]],0) -> 0.058064516 | K19: =IFERROR(tblTransportadora[[#This Row],[Entregados]]/tblTransportadora[[#This Row],[Pedidos]],0) -> 0.53677419
B20: TRANSITO | C20: =IFERROR(COUNTIFS(tblPedidos[estado_operativo],B20),0) -> 92 | F20: VELOCES | G20: =COUNTIFS(tblPedidos[transportadora],tblTransportadora[[#This Row],[Transportadora]]) -> 26 | H20: =COUNTIFS(tblPedidos[transportadora],tblTransportadora[[#This Row],[Transportadora]],tblPedidos[estado_operativo],"ENTREGADO") -> 15 | I20: =COUNTIFS(tblPedidos[transportadora],tblTransportadora[[#This Row],[Transportadora]],tblPedidos[estado_operativo],"DEVOLUCION") -> 3 | J20: =IFERROR(tblTransportadora[[#This Row],[Devolución]]/tblTransportadora[[#This Row],[Pedidos]],0) -> 0.11538462 | K20: =IFERROR(tblTransportadora[[#This Row],[Entregados]]/tblTransportadora[[#This Row],[Pedidos]],0) -> 0.57692308
B21: DESTINO | C21: =IFERROR(COUNTIFS(tblPedidos[estado_operativo],B21),0) -> 16 | F21: COORDINADORA | G21: =COUNTIFS(tblPedidos[transportadora],tblTransportadora[[#This Row],[Transportadora]]) -> 0 | H21: =COUNTIFS(tblPedidos[transportadora],tblTransportadora[[#This Row],[Transportadora]],tblPedidos[estado_operativo],"ENTREGADO") -> 0 | I21: =COUNTIFS(tblPedidos[transportadora],tblTransportadora[[#This Row],[Transportadora]],tblPedidos[estado_operativo],"DEVOLUCION") -> 0 | J21: =IFERROR(tblTransportadora[[#This Row],[Devolución]]/tblTransportadora[[#This Row],[Pedidos]],0) -> 0 | K21: =IFERROR(tblTransportadora[[#This Row],[Entregados]]/tblTransportadora[[#This Row],[Pedidos]],0) -> 0
B22: REPARTO | C22: =IFERROR(COUNTIFS(tblPedidos[estado_operativo],B22),0) -> 31 | I22: =IF(H22="","",COUNTIF(#REF!,H22)) | J22: =IF(H22="","",COUNTIFS(#REF!,H22,#REF!,"ENTREGADO")) | K22: =IF(H22="","",COUNTIFS(#REF!,H22,#REF!,"DEVOLUCIÓN")) | L22: =IF(H22="","",IFERROR(K22/(J22+K22),0))
B23: ENTREGADO | C23: =IFERROR(COUNTIFS(tblPedidos[estado_operativo],B23),0) -> 567 | I23: =IF(H23="","",COUNTIF(#REF!,H23)) | J23: =IF(H23="","",COUNTIFS(#REF!,H23,#REF!,"ENTREGADO")) | K23: =IF(H23="","",COUNTIFS(#REF!,H23,#REF!,"DEVOLUCIÓN")) | L23: =IF(H23="","",IFERROR(K23/(J23+K23),0))
B24: DEVOLUCION | C24: =IFERROR(COUNTIFS(tblPedidos[estado_operativo],B24),0) -> 54 | I24: =IF(H24="","",COUNTIF(#REF!,H24)) | J24: =IF(H24="","",COUNTIFS(#REF!,H24,#REF!,"ENTREGADO")) | K24: =IF(H24="","",COUNTIFS(#REF!,H24,#REF!,"DEVOLUCIÓN")) | L24: =IF(H24="","",IFERROR(K24/(J24+K24),0))
B25: NOVEDAD | C25: =IFERROR(COUNTIFS(tblPedidos[estado_operativo],B25),0) -> 28 | I25: =IF(H25="","",COUNTIF(#REF!,H25)) | J25: =IF(H25="","",COUNTIFS(#REF!,H25,#REF!,"ENTREGADO")) | K25: =IF(H25="","",COUNTIFS(#REF!,H25,#REF!,"DEVOLUCIÓN")) | L25: =IF(H25="","",IFERROR(K25/(J25+K25),0))
B26: NOVEDAD SOLUCIONADA | C26: =IFERROR(COUNTIFS(tblPedidos[estado_operativo],B26),0) -> 5
B27: OFICINA | C27: =IFERROR(COUNTIFS(tblPedidos[estado_operativo],B27),0) -> 55
B28: OFICINA 1 | C28: =IFERROR(COUNTIFS(tblPedidos[estado_operativo],B28),0) -> 0
B29: CANCELADO | C29: =IFERROR(COUNTIFS(tblPedidos[estado_operativo],B29),0) -> 18
B30: SINIESTRO / EXTRAVIADO | C30: =IFERROR(COUNTIFS(tblPedidos[estado_operativo],B30),0) -> 0
B31: SIN MAPEAR | C31: =IFERROR(COUNTIFS(tblPedidos[estado_operativo],B31),0) -> 0
B33: PAUTA | C33: VALOR
B34: SEMANA 1
B35: SEMANA 2
B36: SEMANA 3
B37: SEMANA 4
B39: TOTAL | C39: =SUM(C34:C37) -> 0

Sheet Estados_Encontrados
A1: Estados encontrados en este export (para ayudarte a mapear)
A3: transportadora | B3: estatus_original | C3: ultimo_movimiento | D3: sugerido
A4: ENVIA | B4: PREPARADO PARA TRANSPORTADORA | C4: PREPARADO PARA TRANSPORTADORA | D4: ORIGEN
A5: INTERRAPIDISIMO | B5: PENDIENTE | C5: PENDIENTE | D5: PENDIENTE
A6: VELOCES | B6: GUIA_GENERADA | C6: GUIA_GENERADA | D6: ORIGEN
